Examen Parcial/ExamenParcialCorreccion/Ejercicio2.vhdl
library ieee;
use ieee.numeric_bit.all;
use IEEE.Std_logic_1164.all;
entity circuit is 
    port(A,B,C,D: in bit;
        X,Y,R,E: out bit);
    end circuit;
architecture test of circuit is 
    signal S,E1,F1:bit;
    begin
        S <= A and B after 1 ns;
        R <= S;
        E1 <= not C after 1 ns;
        E <= E1;
        F1 <= (B nand A) nand D after 1 ns;
        X <= (E1 or S) or F1 after 1 ns;
        Y <= F1;
    end test;

Examen Parcial/ExamenParcialCorreccion/Ejercicio2_tb.vhdl

library IEEE;
use IEEE.Std_logic_1164.all;
use IEEE.Numeric_Std.all;

entity circuit_tb is
end;

architecture bench of circuit_tb is

  component circuit 
      port(A,B,C,D: in bit;
          X,Y,R,E: out bit);
      end component;

  signal A,B,C,D: bit;
  signal X,Y,R,E: bit;

begin

  uut: circuit port map ( A => A,
                          B => B,
                          C => C,
                          D => D,
                          R => R,
                          X => X,
                          E => E,
                          Y => Y );

  stimulus: process
  begin 
  
    -- Put initialisation code here
   
    A <= '0';
    B <= '0';
    C <= '0';
    D <= '0';
    wait for 1 ns;
    A <= '1';
    B <= '1';
    C <= '0';
    D <= '1';
    wait for 1 ns;
    A <= '1';
    B <= '1';
    C <= '0';
    D <= '1';
    wait for 1 ns;
    A <= '0';
    B <= '1';
    C <= '1';
    D <= '1';
    wait for 1 ns;
    A <= '0';
    B <= '1';
    C <= '1';
    D <= '1';
    wait for 1 ns;
    A <= '0';
    B <= '0';
    C <= '1';
    D <= '1';
    wait for 1 ns;
    A <= '0';
    B <= '0';
    C <= '1';
    D <= '1';
    wait for 1 ns;
    A <= '0';
    B <= '0';
    C <= '1';
    D <= '0';
    wait for 1 ns;
    A <= '0';
    B <= '0';
    C <= '1';
    D <= '0';
    wait for 1 ns;
    A <= '0';
    B <= '1';
    C <= '0';
    D <= '0';
    wait for 1 ns;
    A <= '1';
    B <= '1';
    C <= '0';
    D <= '0';
    wait for 1 ns;
    A <= '1';
    B <= '1';
    C <= '0';
    D <= '0';
    wait for 1 ns;
    A <= '1';
    B <= '1';
    C <= '1';
    D <= '1';
    wait for 1 ns;
    A <= '0';
    B <= '1';
    C <= '1';
    D <= '1';
    wait for 1 ns;
    A <= '0';
    B <= '1';
    C <= '1';
    D <= '1';
    wait for 1 ns;
    A <= '0';
    B <= '0';
    C <= '0';
    D <= '1';
    wait for 1 ns;

    -- Put test bench stimulus code here

    wait;
  end process;


end;

Examen Parcial/ExamenParcialCorreccion/Ejercicio2_tb.vcd
$date
  Fri Apr 17 09:45:55 2020
$end
$version
  GHDL v0
$end
$timescale
  1 fs
$end
$scope module standard $end
$upscope $end
$scope module std_logic_1164 $end
$upscope $end
$scope module numeric_std $end
$upscope $end
$scope module numeric_bit $end
$upscope $end
$scope module circuit_tb $end
$var reg 1 ! a $end
$var reg 1 " b $end
$var reg 1 # c $end
$var reg 1 $ d $end
$var reg 1 % x $end
$var reg 1 & y $end
$var reg 1 ' r $end
$var reg 1 ( e $end
$scope module uut $end
$var reg 1 ) a $end
$var reg 1 * b $end
$var reg 1 + c $end
$var reg 1 , d $end
$var reg 1 - x $end
$var reg 1 . y $end
$var reg 1 / r $end
$var reg 1 0 e $end
$var reg 1 1 s $end
$var reg 1 2 e1 $end
$var reg 1 3 f1 $end
$upscope $end
$upscope $end
$enddefinitions $end
#0
0!
0"
0#
0$
0%
0&
0'
0(
0)
0*
0+
0,
0-
0.
0/
00
01
02
03
#1000000
1!
1"
1$
1&
1(
1)
1*
1,
0-
1.
10
12
13
#2000000
1%
1'
1-
1/
11
#3000000
0!
1#
0)
1+
1-
#4000000
0&
0'
0(
0.
0/
00
01
02
03
#5000000
0"
0%
0*
0-
#6000000
#7000000
0$
0,
#8000000
1&
1.
13
#9000000
1"
0#
1%
1*
0+
1-
#10000000
1!
1(
1)
10
12
#11000000
1'
1-
1/
11
#12000000
1#
1$
1+
1,
1-
#13000000
0!
0(
0)
00
02
#14000000
0&
0'
1-
0.
0/
01
03
#15000000
0"
0#
0%
0*
0+
0-
#16000000
1(
10
12
#17000000
1%
1-
