Practica_5_simulacion/jk.vhdl
library ieee;
use ieee.std_logic_1164.all;

entity JKFF is
port(
j: in std_logic;
k: in std_logic;
clk: in std_logic;
rst: in std_logic;
q: out std_logic;
qb: out std_logic);
end JKFF;

architecture behavioral of JKFF is
signal temp : std_logic;
begin

process(j,k,clk,rst)
begin

if(rst='1') then
 temp <= '0';
elsif (rising_edge(clk)) then
 if(j/=k) then
  temp <= j;
 elsif(j='1' and k='1') then
  temp <= not temp;
  elsif(j='0' and k='0') then
  temp <= temp;
 end if;
end if;
end process;

q <= temp;
qb <= not temp;

end behavioral;

Practica_3_codigo_VHDL/counter.vhdl
library ieee;
use ieee.std_logic_1164.all;

entity FourBitSynchCounter is
	port (Clk, rst: in std_logic; Q0, Q1, Q2, Q3, Q0b, Q1b, Q2b, Q3b: inout std_logic);
end entity FourBitSynchCounter;

architecture LogicOperation of FourBitSynchCounter is
	component jkff is
		port (J, K, Clk, rst: in std_logic; Q, Qb: out std_logic);
	end component jkff;
	
	signal J1, J2, J3: std_logic;
	begin
	J1 <= Q0;
	J2 <= Q1 and Q0;
	J3 <= Q0 and Q1 and Q2;
	
	
	FF0: jkff port map (J => '1', K => '1', rst => rst, Clk => Clk, Q => Q0, Qb => Q0b);
	FF1: jkff port map (J => J1, K => J1, rst => rst, Clk => Clk, Q => Q1, Qb => Q1b);
	FF2: jkff port map (J => J2, K => J2, rst => rst, Clk => Clk, Q => Q2, Qb => Q2b);
	FF3: jkff port map (J => J3, K => J3, rst => rst, Clk => Clk, Q => Q3, Qb => Q3b);
	
end architecture LogicOperation;

Practica_3_codigo_VHDL/counter_tb.vhdl
library ieee;
use ieee.std_logic_1164.all;

entity counter_tb is
end counter_tb;

architecture behav of counter_tb is
	component FourBitSynchCounter is
		port (Clk, rst: in std_logic; Q0, Q1, Q2, Q3, Q0b, Q1b, Q2b, Q3b: inout std_logic);
	end component FourBitSynchCounter;
	
	signal Clk : std_logic := '0';
	signal rst : std_logic := '0';
	signal Q0, Q1, Q2, Q3, Q0b, Q1b, Q2b, Q3b : std_logic;
	
	constant clk_period : time := 10 ns;
	
	begin
	
	counter: FourBitSynchCounter port map (Clk => Clk, rst => rst, Q0 => Q0, Q1 => Q1, Q2 => Q2, Q3 => Q3, Q0b => Q0b, Q1b => Q1b, Q2b => Q2b, Q3b => Q3b);
	
	clk_process :process
	begin
	clk <= '0';
	wait for clk_period/2;
	clk <= '1';
	wait for clk_period/2;
	end process;
	
	startup : process
	begin
	
	rst <= '1';
	wait for 5 ns;
	
	rst <= '0';
	wait for 100 ms;
	
	end process;
	
end architecture behav;

Practica_3_codigo_VHDL/counter.vcd
$date
  Sat Mar 28 02:38:27 2020
$end
$version
  GHDL v0
$end
$timescale
  1 fs
$end
$scope module standard $end
$upscope $end
$scope module std_logic_1164 $end
$upscope $end
$scope module counter_tb $end
$var reg 1 ! clk $end
$var reg 1 " rst $end
$var reg 1 # q0 $end
$var reg 1 $ q1 $end
$var reg 1 % q2 $end
$var reg 1 & q3 $end
$var reg 1 ' q0b $end
$var reg 1 ( q1b $end
$var reg 1 ) q2b $end
$var reg 1 * q3b $end
$scope module counter $end
$var reg 1 + clk $end
$var reg 1 , rst $end
$var reg 1 - q0 $end
$var reg 1 . q1 $end
$var reg 1 / q2 $end
$var reg 1 0 q3 $end
$var reg 1 1 q0b $end
$var reg 1 2 q1b $end
$var reg 1 3 q2b $end
$var reg 1 4 q3b $end
$var reg 1 5 j1 $end
$var reg 1 6 j2 $end
$var reg 1 7 j3 $end
$scope module ff0 $end
$var reg 1 8 j $end
$var reg 1 9 k $end
$var reg 1 : clk $end
$var reg 1 ; rst $end
$var reg 1 < q $end
$var reg 1 = qb $end
$var reg 1 > temp $end
$upscope $end
$scope module ff1 $end
$var reg 1 ? j $end
$var reg 1 @ k $end
$var reg 1 A clk $end
$var reg 1 B rst $end
$var reg 1 C q $end
$var reg 1 D qb $end
$var reg 1 E temp $end
$upscope $end
$scope module ff2 $end
$var reg 1 F j $end
$var reg 1 G k $end
$var reg 1 H clk $end
$var reg 1 I rst $end
$var reg 1 J q $end
$var reg 1 K qb $end
$var reg 1 L temp $end
$upscope $end
$scope module ff3 $end
$var reg 1 M j $end
$var reg 1 N k $end
$var reg 1 O clk $end
$var reg 1 P rst $end
$var reg 1 Q q $end
$var reg 1 R qb $end
$var reg 1 S temp $end
$upscope $end
$upscope $end
$upscope $end
$enddefinitions $end
#0
0!
1"
0#
0$
0%
0&
1'
1(
1)
1*
0+
1,
0-
0.
0/
00
11
12
13
14
05
06
07
18
19
0:
1;
0<
1=
0>
0?
0@
0A
1B
0C
1D
0E
0F
0G
0H
1I
0J
1K
0L
0M
0N
0O
1P
0Q
1R
0S
#5000000
1!
0"
1#
0'
1+
0,
1-
01
15
1:
0;
1<
0=
1>
1?
1@
1A
0B
1H
0I
1O
0P
#10000000
0!
0+
0:
0A
0H
0O
#15000000
1!
0#
1$
1'
0(
1+
0-
1.
11
02
05
1:
0<
1=
0>
0?
0@
1A
1C
0D
1E
1H
1O
#20000000
0!
0+
0:
0A
0H
0O
#25000000
1!
1#
0'
1+
1-
01
15
16
1:
1<
0=
1>
1?
1@
1A
1F
1G
1H
1O
#30000000
0!
0+
0:
0A
0H
0O
#35000000
1!
0#
0$
1%
1'
1(
0)
1+
0-
0.
1/
11
12
03
05
06
1:
0<
1=
0>
0?
0@
1A
0C
1D
0E
0F
0G
1H
1J
0K
1L
1O
#40000000
0!
0+
0:
0A
0H
0O
#45000000
1!
1#
0'
1+
1-
01
15
1:
1<
0=
1>
1?
1@
1A
1H
1O
#50000000
0!
0+
0:
0A
0H
0O
#55000000
1!
0#
1$
1'
0(
1+
0-
1.
11
02
05
1:
0<
1=
0>
0?
0@
1A
1C
0D
1E
1H
1O
#60000000
0!
0+
0:
0A
0H
0O
#65000000
1!
1#
0'
1+
1-
01
15
16
17
1:
1<
0=
1>
1?
1@
1A
1F
1G
1H
1M
1N
1O
#70000000
0!
0+
0:
0A
0H
0O
#75000000
1!
0#
0$
0%
1&
1'
1(
1)
0*
1+
0-
0.
0/
10
11
12
13
04
05
06
07
1:
0<
1=
0>
0?
0@
1A
0C
1D
0E
0F
0G
1H
0J
1K
0L
0M
0N
1O
1Q
0R
1S
#80000000
0!
0+
0:
0A
0H
0O
#85000000
1!
1#
0'
1+
1-
01
15
1:
1<
0=
1>
1?
1@
1A
1H
1O
#90000000
0!
0+
0:
0A
0H
0O
#95000000
1!
0#
1$
1'
0(
1+
0-
1.
11
02
05
1:
0<
1=
0>
0?
0@
1A
1C
0D
1E
1H
1O
#100000000
0!
0+
0:
0A
0H
0O
#105000000
1!
1#
0'
1+
1-
01
15
16
1:
1<
0=
1>
1?
1@
1A
1F
1G
1H
1O
#110000000
0!
0+
0:
0A
0H
0O
#115000000
1!
0#
0$
1%
1'
1(
0)
1+
0-
0.
1/
11
12
03
05
06
1:
0<
1=
0>
0?
0@
1A
0C
1D
0E
0F
0G
1H
1J
0K
1L
1O
#120000000
0!
0+
0:
0A
0H
0O
#125000000
1!
1#
0'
1+
1-
01
15
1:
1<
0=
1>
1?
1@
1A
1H
1O
#130000000
0!
0+
0:
0A
0H
0O
#135000000
1!
0#
1$
1'
0(
1+
0-
1.
11
02
05
1:
0<
1=
0>
0?
0@
1A
1C
0D
1E
1H
1O
#140000000
0!
0+
0:
0A
0H
0O
#145000000
1!
1#
0'
1+
1-
01
15
16
17
1:
1<
0=
1>
1?
1@
1A
1F
1G
1H
1M
1N
1O
#150000000
0!
0+
0:
0A
0H
0O
#155000000
1!
0#
0$
0%
0&
1'
1(
1)
1*
1+
0-
0.
0/
00
11
12
13
14
05
06
07
1:
0<
1=
0>
0?
0@
1A
0C
1D
0E
0F
0G
1H
0J
1K
0L
0M
0N
1O
0Q
1R
0S
#160000000
0!
0+
0:
0A
0H
0O
#165000000
1!
1#
0'
1+
1-
01
15
1:
1<
0=
1>
1?
1@
1A
1H
1O
#170000000
0!
0+
0:
0A
0H
0O
#175000000
1!
0#
1$
1'
0(
1+
0-
1.
11
02
05
1:
0<
1=
0>
0?
0@
1A
1C
0D
1E
1H
1O
#180000000
0!
0+
0:
0A
0H
0O
#185000000
1!
1#
0'
1+
1-
01
15
16
1:
1<
0=
1>
1?
1@
1A
1F
1G
1H
1O
#190000000
0!
0+
0:
0A
0H
0O
#195000000
1!
0#
0$
1%
1'
1(
0)
1+
0-
0.
1/
11
12
03
05
06
1:
0<
1=
0>
0?
0@
1A
0C
1D
0E
0F
0G
1H
1J
0K
1L
1O
#200000000
0!
0+
0:
0A
0H
0O
#205000000
1!
1#
0'
1+
1-
01
15
1:
1<
0=
1>
1?
1@
1A
1H
1O
#210000000
0!
0+
0:
0A
0H
0O
#215000000
1!
0#
1$
1'
0(
1+
0-
1.
11
02
05
1:
0<
1=
0>
0?
0@
1A
1C
0D
1E
1H
1O
#220000000
0!
0+
0:
0A
0H
0O
#225000000
1!
1#
0'
1+
1-
01
15
16
17
1:
1<
0=
1>
1?
1@
1A
1F
1G
1H
1M
1N
1O
#230000000
0!
0+
0:
0A
0H
0O
#235000000
1!
0#
0$
0%
1&
1'
1(
1)
0*
1+
0-
0.
0/
10
11
12
13
04
05
06
07
1:
0<
1=
0>
0?
0@
1A
0C
1D
0E
0F
0G
1H
0J
1K
0L
0M
0N
1O
1Q
0R
1S
#240000000
0!
0+
0:
0A
0H
0O
#245000000
1!
1#
0'
1+
1-
01
15
1:
1<
0=
1>
1?
1@
1A
1H
1O
#250000000
0!
0+
0:
0A
0H
0O
#255000000
1!
0#
1$
1'
0(
1+
0-
1.
11
02
05
1:
0<
1=
0>
0?
0@
1A
1C
0D
1E
1H
1O
#260000000
0!
0+
0:
0A
0H
0O
#265000000
1!
1#
0'
1+
1-
01
15
16
1:
1<
0=
1>
1?
1@
1A
1F
1G
1H
1O
#270000000
0!
0+
0:
0A
0H
0O
#275000000
1!
0#
0$
1%
1'
1(
0)
1+
0-
0.
1/
11
12
03
05
06
1:
0<
1=
0>
0?
0@
1A
0C
1D
0E
0F
0G
1H
1J
0K
1L
1O
#280000000
0!
0+
0:
0A
0H
0O
#285000000
1!
1#
0'
1+
1-
01
15
1:
1<
0=
1>
1?
1@
1A
1H
1O
#290000000
0!
0+
0:
0A
0H
0O
#295000000
1!
0#
1$
1'
0(
1+
0-
1.
11
02
05
1:
0<
1=
0>
0?
0@
1A
1C
0D
1E
1H
1O
#300000000
0!
0+
0:
0A
0H
0O
#305000000
1!
1#
0'
1+
1-
01
15
16
17
1:
1<
0=
1>
1?
1@
1A
1F
1G
1H
1M
1N
1O
#310000000
0!
0+
0:
0A
0H
0O
#315000000
1!
0#
0$
0%
0&
1'
1(
1)
1*
1+
0-
0.
0/
00
11
12
13
14
05
06
07
1:
0<
1=
0>
0?
0@
1A
0C
1D
0E
0F
0G
1H
0J
1K
0L
0M
0N
1O
0Q
1R
0S
#320000000
0!
0+
0:
0A
0H
0O
#325000000
1!
1#
0'
1+
1-
01
15
1:
1<
0=
1>
1?
1@
1A
1H
1O
#330000000
0!
0+
0:
0A
0H
0O
#335000000
1!
0#
1$
1'
0(
1+
0-
1.
11
02
05
1:
0<
1=
0>
0?
0@
1A
1C
0D
1E
1H
1O
#340000000
0!
0+
0:
0A
0H
0O
#345000000
1!
1#
0'
1+
1-
01
15
16
1:
1<
0=
1>
1?
1@
1A
1F
1G
1H
1O
#350000000
0!
0+
0:
0A
0H
0O
#355000000
1!
0#
0$
1%
1'
1(
0)
1+
0-
0.
1/
11
12
03
05
06
1:
0<
1=
0>
0?
0@
1A
0C
1D
0E
0F
0G
1H
1J
0K
1L
1O
#360000000
0!
0+
0:
0A
0H
0O
#365000000
1!
1#
0'
1+
1-
01
15
1:
1<
0=
1>
1?
1@
1A
1H
1O
#370000000
0!
0+
0:
0A
0H
0O
#375000000
1!
0#
1$
1'
0(
1+
0-
1.
11
02
05
1:
0<
1=
0>
0?
0@
1A
1C
0D
1E
1H
1O
#380000000
0!
0+
0:
0A
0H
0O
#385000000
1!
1#
0'
1+
1-
01
15
16
17
1:
1<
0=
1>
1?
1@
1A
1F
1G
1H
1M
1N
1O
#390000000
0!
0+
0:
0A
0H
0O
#395000000
1!
0#
0$
0%
1&
1'
1(
1)
0*
1+
0-
0.
0/
10
11
12
13
04
05
06
07
1:
0<
1=
0>
0?
0@
1A
0C
1D
0E
0F
0G
1H
0J
1K
0L
0M
0N
1O
1Q
0R
1S
#400000000
0!
0+
0:
0A
0H
0O
#405000000
1!
1#
0'
1+
1-
01
15
1:
1<
0=
1>
1?
1@
1A
1H
1O
#410000000
0!
0+
0:
0A
0H
0O
#415000000
1!
0#
1$
1'
0(
1+
0-
1.
11
02
05
1:
0<
1=
0>
0?
0@
1A
1C
0D
1E
1H
1O
#420000000
0!
0+
0:
0A
0H
0O
#425000000
1!
1#
0'
1+
1-
01
15
16
1:
1<
0=
1>
1?
1@
1A
1F
1G
1H
1O
#430000000
0!
0+
0:
0A
0H
0O
#435000000
1!
0#
0$
1%
1'
1(
0)
1+
0-
0.
1/
11
12
03
05
06
1:
0<
1=
0>
0?
0@
1A
0C
1D
0E
0F
0G
1H
1J
0K
1L
1O
#440000000
0!
0+
0:
0A
0H
0O
#445000000
1!
1#
0'
1+
1-
01
15
1:
1<
0=
1>
1?
1@
1A
1H
1O
#450000000
0!
0+
0:
0A
0H
0O
#455000000
1!
0#
1$
1'
0(
1+
0-
1.
11
02
05
1:
0<
1=
0>
0?
0@
1A
1C
0D
1E
1H
1O
#460000000
0!
0+
0:
0A
0H
0O
#465000000
1!
1#
0'
1+
1-
01
15
16
17
1:
1<
0=
1>
1?
1@
1A
1F
1G
1H
1M
1N
1O
#470000000
0!
0+
0:
0A
0H
0O
#475000000
1!
0#
0$
0%
0&
1'
1(
1)
1*
1+
0-
0.
0/
00
11
12
13
14
05
06
07
1:
0<
1=
0>
0?
0@
1A
0C
1D
0E
0F
0G
1H
0J
1K
0L
0M
0N
1O
0Q
1R
0S
#480000000
0!
0+
0:
0A
0H
0O
#485000000
1!
1#
0'
1+
1-
01
15
1:
1<
0=
1>
1?
1@
1A
1H
1O
#490000000
0!
0+
0:
0A
0H
0O
#495000000
1!
0#
1$
1'
0(
1+
0-
1.
11
02
05
1:
0<
1=
0>
0?
0@
1A
1C
0D
1E
1H
1O
#500000000
0!
0+
0:
0A
0H
0O
#505000000
1!
1#
0'
1+
1-
01
15
16
1:
1<
0=
1>
1?
1@
1A
1F
1G
1H
1O
#510000000
0!
0+
0:
0A
0H
0O
#515000000
1!
0#
0$
1%
1'
1(
0)
1+
0-
0.
1/
11
12
03
05
06
1:
0<
1=
0>
0?
0@
1A
0C
1D
0E
0F
0G
1H
1J
0K
1L
1O
#520000000
0!
0+
0:
0A
0H
0O
#525000000
1!
1#
0'
1+
1-
01
15
1:
1<
0=
1>
1?
1@
1A
1H
1O
#530000000
0!
0+
0:
0A
0H
0O
#535000000
1!
0#
1$
1'
0(
1+
0-
1.
11
02
05
1:
0<
1=
0>
0?
0@
1A
1C
0D
1E
1H
1O
#540000000
0!
0+
0:
0A
0H
0O
#545000000
1!
1#
0'
1+
1-
01
15
16
17
1:
1<
0=
1>
1?
1@
1A
1F
1G
1H
1M
1N
1O
#550000000
0!
0+
0:
0A
0H
0O
#555000000
1!
0#
0$
0%
1&
1'
1(
1)
0*
1+
0-
0.
0/
10
11
12
13
04
05
06
07
1:
0<
1=
0>
0?
0@
1A
0C
1D
0E
0F
0G
1H
0J
1K
0L
0M
0N
1O
1Q
0R
1S
#560000000
0!
0+
0:
0A
0H
0O
#565000000
1!
1#
0'
1+
1-
01
15
1:
1<
0=
1>
1?
1@
1A
1H
1O
#570000000
0!
0+
0:
0A
0H
0O
#575000000
1!
0#
1$
1'
0(
1+
0-
1.
11
02
05
1:
0<
1=
0>
0?
0@
1A
1C
0D
1E
1H
1O
#580000000
0!
0+
0:
0A
0H
0O
#585000000
1!
1#
0'
1+
1-
01
15
16
1:
1<
0=
1>
1?
1@
1A
1F
1G
1H
1O
#590000000
0!
0+
0:
0A
0H
0O
#595000000
1!
0#
0$
1%
1'
1(
0)
1+
0-
0.
1/
11
12
03
05
06
1:
0<
1=
0>
0?
0@
1A
0C
1D
0E
0F
0G
1H
1J
0K
1L
1O
