Practica_5_simulacion/jk.vhdl
library ieee;
use ieee.std_logic_1164.all;

entity JKFF is
port(
j: in std_logic;
k: in std_logic;
clk: in std_logic;
rst: in std_logic;
q: out std_logic;
qb: out std_logic);
end JKFF;

architecture behavioral of JKFF is
signal temp : std_logic;
begin

process(j,k,clk,rst)
begin

if(rst='1') then
 temp <= '0';
elsif (rising_edge(clk)) then
 if(j/=k) then
  temp <= j;
 elsif(j='1' and k='1') then
  temp <= not temp;
  elsif(j='0' and k='0') then
  temp <= temp;
 end if;
end if;
end process;

q <= temp;
qb <= not temp;

end behavioral;

Practica_3_codigo_VHDL/decadeC.vhdl
library ieee;
use ieee.std_logic_1164.all;

entity FourBitSynchDecadeCounter is
	port (Clk, rst: in std_logic; Q0, Q1, Q2, Q3, Q0b, Q1b, Q2b, Q3b: inout std_logic);
end entity FourBitSynchDecadeCounter;

architecture LogicOperation of FourBitSynchDecadeCounter is
	component jkff is
		port (J, K, Clk, rst: in std_logic; Q, Qb: out std_logic);
	end component jkff;
	
	signal J1, J2, J3, K1, K3: std_logic;
	begin
	J1 <= Q0 and not Q3;
	J2 <= Q1 and Q0;
	J3 <= Q0 and Q1 and Q2;
	K1 <= Q0;
	K3 <= Q0;
	
	
	FF0: jkff port map (J => '1', K => '1', rst => rst, Clk => Clk, Q => Q0, Qb => Q0b);
	FF1: jkff port map (J => J1, K => K1, rst => rst, Clk => Clk, Q => Q1, Qb => Q1b);
	FF2: jkff port map (J => J2, K => J2, rst => rst, Clk => Clk, Q => Q2, Qb => Q2b);
	FF3: jkff port map (J => J3, K => K3, rst => rst, Clk => Clk, Q => Q3, Qb => Q3b);
	
end architecture LogicOperation;

Practica_3_codigo_VHDL/decadeC_tb.vhdl
library ieee;
use ieee.std_logic_1164.all;

entity decadeC_tb is
end decadeC_tb;

architecture behav of decadeC_tb is
	component FourBitSynchDecadeCounter is
		port (Clk, rst: in std_logic; Q0, Q1, Q2, Q3, Q0b, Q1b, Q2b, Q3b: inout std_logic);
	end component FourBitSynchDecadeCounter;
	
	signal Clk : std_logic := '0';
	signal rst : std_logic := '0';
	signal Q0, Q1, Q2, Q3, Q0b, Q1b, Q2b, Q3b : std_logic;
	
	constant clk_period : time := 10 ns;
	
	begin
	
	counter: FourBitSynchDecadeCounter port map (Clk => Clk, rst => rst, Q0 => Q0, Q1 => Q1, Q2 => Q2, Q3 => Q3, Q0b => Q0b, Q1b => Q1b, Q2b => Q2b, Q3b => Q3b);
	
	clk_process :process
	begin
	clk <= '0';
	wait for clk_period/2;
	clk <= '1';
	wait for clk_period/2;
	end process;
	
	startup : process
	begin
	
	rst <= '1';
	wait for 5 ns;
	
	rst <= '0';
	wait for 100 ms;
	
	end process;
	
end architecture behav;

Practica_3_codigo_VHDL/decadeC_tb.vcd
$date
  Sat Mar 28 02:28:52 2020
$end
$version
  GHDL v0
$end
$timescale
  1 fs
$end
$scope module standard $end
$upscope $end
$scope module std_logic_1164 $end
$upscope $end
$scope module decadec_tb $end
$var reg 1 ! clk $end
$var reg 1 " rst $end
$var reg 1 # q0 $end
$var reg 1 $ q1 $end
$var reg 1 % q2 $end
$var reg 1 & q3 $end
$var reg 1 ' q0b $end
$var reg 1 ( q1b $end
$var reg 1 ) q2b $end
$var reg 1 * q3b $end
$scope module counter $end
$var reg 1 + clk $end
$var reg 1 , rst $end
$var reg 1 - q0 $end
$var reg 1 . q1 $end
$var reg 1 / q2 $end
$var reg 1 0 q3 $end
$var reg 1 1 q0b $end
$var reg 1 2 q1b $end
$var reg 1 3 q2b $end
$var reg 1 4 q3b $end
$var reg 1 5 j1 $end
$var reg 1 6 j2 $end
$var reg 1 7 j3 $end
$var reg 1 8 k1 $end
$var reg 1 9 k3 $end
$scope module ff0 $end
$var reg 1 : j $end
$var reg 1 ; k $end
$var reg 1 < clk $end
$var reg 1 = rst $end
$var reg 1 > q $end
$var reg 1 ? qb $end
$var reg 1 @ temp $end
$upscope $end
$scope module ff1 $end
$var reg 1 A j $end
$var reg 1 B k $end
$var reg 1 C clk $end
$var reg 1 D rst $end
$var reg 1 E q $end
$var reg 1 F qb $end
$var reg 1 G temp $end
$upscope $end
$scope module ff2 $end
$var reg 1 H j $end
$var reg 1 I k $end
$var reg 1 J clk $end
$var reg 1 K rst $end
$var reg 1 L q $end
$var reg 1 M qb $end
$var reg 1 N temp $end
$upscope $end
$scope module ff3 $end
$var reg 1 O j $end
$var reg 1 P k $end
$var reg 1 Q clk $end
$var reg 1 R rst $end
$var reg 1 S q $end
$var reg 1 T qb $end
$var reg 1 U temp $end
$upscope $end
$upscope $end
$upscope $end
$enddefinitions $end
#0
0!
1"
0#
0$
0%
0&
1'
1(
1)
1*
0+
1,
0-
0.
0/
00
11
12
13
14
05
06
07
08
09
1:
1;
0<
1=
0>
1?
0@
0A
0B
0C
1D
0E
1F
0G
0H
0I
0J
1K
0L
1M
0N
0O
0P
0Q
1R
0S
1T
0U
#5000000
1!
0"
1#
0'
1+
0,
1-
01
15
18
19
1<
0=
1>
0?
1@
1A
1B
1C
0D
1J
0K
1P
1Q
0R
#10000000
0!
0+
0<
0C
0J
0Q
#15000000
1!
0#
1$
1'
0(
1+
0-
1.
11
02
05
08
09
1<
0>
1?
0@
0A
0B
1C
1E
0F
1G
1J
0P
1Q
#20000000
0!
0+
0<
0C
0J
0Q
#25000000
1!
1#
0'
1+
1-
01
15
16
18
19
1<
1>
0?
1@
1A
1B
1C
1H
1I
1J
1P
1Q
#30000000
0!
0+
0<
0C
0J
0Q
#35000000
1!
0#
0$
1%
1'
1(
0)
1+
0-
0.
1/
11
12
03
05
06
08
09
1<
0>
1?
0@
0A
0B
1C
0E
1F
0G
0H
0I
1J
1L
0M
1N
0P
1Q
#40000000
0!
0+
0<
0C
0J
0Q
#45000000
1!
1#
0'
1+
1-
01
15
18
19
1<
1>
0?
1@
1A
1B
1C
1J
1P
1Q
#50000000
0!
0+
0<
0C
0J
0Q
#55000000
1!
0#
1$
1'
0(
1+
0-
1.
11
02
05
08
09
1<
0>
1?
0@
0A
0B
1C
1E
0F
1G
1J
0P
1Q
#60000000
0!
0+
0<
0C
0J
0Q
#65000000
1!
1#
0'
1+
1-
01
15
16
17
18
19
1<
1>
0?
1@
1A
1B
1C
1H
1I
1J
1O
1P
1Q
#70000000
0!
0+
0<
0C
0J
0Q
#75000000
1!
0#
0$
0%
1&
1'
1(
1)
0*
1+
0-
0.
0/
10
11
12
13
04
05
06
07
08
09
1<
0>
1?
0@
0A
0B
1C
0E
1F
0G
0H
0I
1J
0L
1M
0N
0O
0P
1Q
1S
0T
1U
#80000000
0!
0+
0<
0C
0J
0Q
#85000000
1!
1#
0'
1+
1-
01
18
19
1<
1>
0?
1@
1B
1C
1J
1P
1Q
#90000000
0!
0+
0<
0C
0J
0Q
#95000000
1!
0#
0&
1'
1*
1+
0-
00
11
14
08
09
1<
0>
1?
0@
0B
1C
1J
0P
1Q
0S
1T
0U
#100000000
0!
0+
0<
0C
0J
0Q
#105000000
1!
1#
0'
1+
1-
01
15
18
19
1<
1>
0?
1@
1A
1B
1C
1J
1P
1Q
#110000000
0!
0+
0<
0C
0J
0Q
#115000000
1!
0#
1$
1'
0(
1+
0-
1.
11
02
05
08
09
1<
0>
1?
0@
0A
0B
1C
1E
0F
1G
1J
0P
1Q
#120000000
0!
0+
0<
0C
0J
0Q
#125000000
1!
1#
0'
1+
1-
01
15
16
18
19
1<
1>
0?
1@
1A
1B
1C
1H
1I
1J
1P
1Q
#130000000
0!
0+
0<
0C
0J
0Q
#135000000
1!
0#
0$
1%
1'
1(
0)
1+
0-
0.
1/
11
12
03
05
06
08
09
1<
0>
1?
0@
0A
0B
1C
0E
1F
0G
0H
0I
1J
1L
0M
1N
0P
1Q
#140000000
0!
0+
0<
0C
0J
0Q
#145000000
1!
1#
0'
1+
1-
01
15
18
19
1<
1>
0?
1@
1A
1B
1C
1J
1P
1Q
#150000000
0!
0+
0<
0C
0J
0Q
#155000000
1!
0#
1$
1'
0(
1+
0-
1.
11
02
05
08
09
1<
0>
1?
0@
0A
0B
1C
1E
0F
1G
1J
0P
1Q
#160000000
0!
0+
0<
0C
0J
0Q
#165000000
1!
1#
0'
1+
1-
01
15
16
17
18
19
1<
1>
0?
1@
1A
1B
1C
1H
1I
1J
1O
1P
1Q
#170000000
0!
0+
0<
0C
0J
0Q
#175000000
1!
0#
0$
0%
1&
1'
1(
1)
0*
1+
0-
0.
0/
10
11
12
13
04
05
06
07
08
09
1<
0>
1?
0@
0A
0B
1C
0E
1F
0G
0H
0I
1J
0L
1M
0N
0O
0P
1Q
1S
0T
1U
#180000000
0!
0+
0<
0C
0J
0Q
#185000000
1!
1#
0'
1+
1-
01
18
19
1<
1>
0?
1@
1B
1C
1J
1P
1Q
#190000000
0!
0+
0<
0C
0J
0Q
#195000000
1!
0#
0&
1'
1*
1+
0-
00
11
14
08
09
1<
0>
1?
0@
0B
1C
1J
0P
1Q
0S
1T
0U
#200000000
0!
0+
0<
0C
0J
0Q
#205000000
1!
1#
0'
1+
1-
01
15
18
19
1<
1>
0?
1@
1A
1B
1C
1J
1P
1Q
#210000000
0!
0+
0<
0C
0J
0Q
#215000000
1!
0#
1$
1'
0(
1+
0-
1.
11
02
05
08
09
1<
0>
1?
0@
0A
0B
1C
1E
0F
1G
1J
0P
1Q
#220000000
0!
0+
0<
0C
0J
0Q
#225000000
1!
1#
0'
1+
1-
01
15
16
18
19
1<
1>
0?
1@
1A
1B
1C
1H
1I
1J
1P
1Q
#230000000
0!
0+
0<
0C
0J
0Q
#235000000
1!
0#
0$
1%
1'
1(
0)
1+
0-
0.
1/
11
12
03
05
06
08
09
1<
0>
1?
0@
0A
0B
1C
0E
1F
0G
0H
0I
1J
1L
0M
1N
0P
1Q
#240000000
0!
0+
0<
0C
0J
0Q
#245000000
1!
1#
0'
1+
1-
01
15
18
19
1<
1>
0?
1@
1A
1B
1C
1J
1P
1Q
#250000000
0!
0+
0<
0C
0J
0Q
#255000000
1!
0#
1$
1'
0(
1+
0-
1.
11
02
05
08
09
1<
0>
1?
0@
0A
0B
1C
1E
0F
1G
1J
0P
1Q
#260000000
0!
0+
0<
0C
0J
0Q
#265000000
1!
1#
0'
1+
1-
01
15
16
17
18
19
1<
1>
0?
1@
1A
1B
1C
1H
1I
1J
1O
1P
1Q
#270000000
0!
0+
0<
0C
0J
0Q
#275000000
1!
0#
0$
0%
1&
1'
1(
1)
0*
1+
0-
0.
0/
10
11
12
13
04
05
06
07
08
09
1<
0>
1?
0@
0A
0B
1C
0E
1F
0G
0H
0I
1J
0L
1M
0N
0O
0P
1Q
1S
0T
1U
#280000000
0!
0+
0<
0C
0J
0Q
#285000000
1!
1#
0'
1+
1-
01
18
19
1<
1>
0?
1@
1B
1C
1J
1P
1Q
#290000000
0!
0+
0<
0C
0J
0Q
#295000000
1!
0#
0&
1'
1*
1+
0-
00
11
14
08
09
1<
0>
1?
0@
0B
1C
1J
0P
1Q
0S
1T
0U
#300000000
0!
0+
0<
0C
0J
0Q
#305000000
1!
1#
0'
1+
1-
01
15
18
19
1<
1>
0?
1@
1A
1B
1C
1J
1P
1Q
#310000000
0!
0+
0<
0C
0J
0Q
#315000000
1!
0#
1$
1'
0(
1+
0-
1.
11
02
05
08
09
1<
0>
1?
0@
0A
0B
1C
1E
0F
1G
1J
0P
1Q
#320000000
0!
0+
0<
0C
0J
0Q
#325000000
1!
1#
0'
1+
1-
01
15
16
18
19
1<
1>
0?
1@
1A
1B
1C
1H
1I
1J
1P
1Q
#330000000
0!
0+
0<
0C
0J
0Q
#335000000
1!
0#
0$
1%
1'
1(
0)
1+
0-
0.
1/
11
12
03
05
06
08
09
1<
0>
1?
0@
0A
0B
1C
0E
1F
0G
0H
0I
1J
1L
0M
1N
0P
1Q
#340000000
0!
0+
0<
0C
0J
0Q
#345000000
1!
1#
0'
1+
1-
01
15
18
19
1<
1>
0?
1@
1A
1B
1C
1J
1P
1Q
#350000000
0!
0+
0<
0C
0J
0Q
#355000000
1!
0#
1$
1'
0(
1+
0-
1.
11
02
05
08
09
1<
0>
1?
0@
0A
0B
1C
1E
0F
1G
1J
0P
1Q
#360000000
0!
0+
0<
0C
0J
0Q
#365000000
1!
1#
0'
1+
1-
01
15
16
17
18
19
1<
1>
0?
1@
1A
1B
1C
1H
1I
1J
1O
1P
1Q
#370000000
0!
0+
0<
0C
0J
0Q
#375000000
1!
0#
0$
0%
1&
1'
1(
1)
0*
1+
0-
0.
0/
10
11
12
13
04
05
06
07
08
09
1<
0>
1?
0@
0A
0B
1C
0E
1F
0G
0H
0I
1J
0L
1M
0N
0O
0P
1Q
1S
0T
1U
#380000000
0!
0+
0<
0C
0J
0Q
#385000000
1!
1#
0'
1+
1-
01
18
19
1<
1>
0?
1@
1B
1C
1J
1P
1Q
#390000000
0!
0+
0<
0C
0J
0Q
#395000000
1!
0#
0&
1'
1*
1+
0-
00
11
14
08
09
1<
0>
1?
0@
0B
1C
1J
0P
1Q
0S
1T
0U
