Practica_5_simulacion/jk.vhdl
library ieee;
use ieee.std_logic_1164.all;

entity JKFF is
port(
j: in std_logic;
k: in std_logic;
clk: in std_logic;
rst: in std_logic;
q: out std_logic;
qb: out std_logic);
end JKFF;

architecture behavioral of JKFF is
signal temp : std_logic;
begin

process(j,k,clk,rst)
begin

if(rst='1') then
 temp <= '0';
elsif (rising_edge(clk)) then
 if(j/=k) then
  temp <= j;
 elsif(j='1' and k='1') then
  temp <= not temp;
  elsif(j='0' and k='0') then
  temp <= temp;
 end if;
end if;
end process;

q <= temp;
qb <= not temp;

end behavioral;

Practica_3_codigo_VHDL/jk_tb.vhdl
LIBRARY ieee;
USE ieee.std_logic_1164.ALL;

ENTITY JKFF_tb IS
END JKFF_tb;

ARCHITECTURE behavior OF JKFF_tb IS 

    COMPONENT JKFF
    PORT(
         j : IN  std_logic;
         k : IN  std_logic;
         clk : IN  std_logic;
         rst : IN  std_logic;
         q : OUT  std_logic;
         qb : OUT  std_logic
        );
    END COMPONENT;
    
   signal j : std_logic := '0';
   signal k : std_logic := '0';
   signal clk : std_logic := '0';
   signal rst : std_logic := '0';
   signal q : std_logic;
   signal qb : std_logic;

   constant clk_period : time := 10 ns;

BEGIN

   uut: entity work.JKFF PORT MAP (
          j => j,
          k => k,
          clk => clk,
          rst => rst,
          q => q,
          qb => qb
        );

  clk_process :process
  begin
  clk <= '0';
  wait for clk_period/2;
  clk <= '1';
  wait for clk_period/2;
  end process;

  stim_proc: process
  begin  

  rst <= '1';
  wait for 50 ns; 

  rst <= '0';
  j <= '0';
  k <= '1';
  wait for 50 ns;
  
  rst <= '0';
  j <= '1'; 
  k <= '0';
  wait for 50 ns;
  
  rst <= '0';
  j <= '1'; 
  k <= '1';
  wait for 50 ns;

  rst <= '0';
  j <= '0'; 
  k <= '0';
  wait;

  end process;

END;

Practica_3_codigo_VHDL/jk_tb.vcd
$date
  Sat Mar 28 02:27:40 2020
$end
$version
  GHDL v0
$end
$timescale
  1 fs
$end
$scope module standard $end
$upscope $end
$scope module std_logic_1164 $end
$upscope $end
$scope module jkff_tb $end
$var reg 1 ! j $end
$var reg 1 " k $end
$var reg 1 # clk $end
$var reg 1 $ rst $end
$var reg 1 % q $end
$var reg 1 & qb $end
$scope module uut $end
$var reg 1 ' j $end
$var reg 1 ( k $end
$var reg 1 ) clk $end
$var reg 1 * rst $end
$var reg 1 + q $end
$var reg 1 , qb $end
$var reg 1 - temp $end
$upscope $end
$upscope $end
$enddefinitions $end
#0
0!
0"
0#
1$
0%
1&
0'
0(
0)
1*
0+
1,
0-
#5000000
1#
1)
#10000000
0#
0)
#15000000
1#
1)
#20000000
0#
0)
#25000000
1#
1)
#30000000
0#
0)
#35000000
1#
1)
#40000000
0#
0)
#45000000
1#
1)
#50000000
1"
0#
0$
1(
0)
0*
#55000000
1#
1)
#60000000
0#
0)
#65000000
1#
1)
#70000000
0#
0)
#75000000
1#
1)
#80000000
0#
0)
#85000000
1#
1)
#90000000
0#
0)
#95000000
1#
1)
#100000000
1!
0"
0#
1'
0(
0)
#105000000
1#
1%
0&
1)
1+
0,
1-
#110000000
0#
0)
#115000000
1#
1)
#120000000
0#
0)
#125000000
1#
1)
#130000000
0#
0)
#135000000
1#
1)
#140000000
0#
0)
#145000000
1#
1)
#150000000
1"
0#
1(
0)
#155000000
1#
0%
1&
1)
0+
1,
0-
#160000000
0#
0)
#165000000
1#
1%
0&
1)
1+
0,
1-
#170000000
0#
0)
#175000000
1#
0%
1&
1)
0+
1,
0-
#180000000
0#
0)
#185000000
1#
1%
0&
1)
1+
0,
1-
#190000000
0#
0)
#195000000
1#
0%
1&
1)
0+
1,
0-
#200000000
0!
0"
0#
0'
0(
0)
