Practica_3_codigo_VHDL/updown.vhdl
-- Escola Politecnica da Universidade de Sao Paulo
-- Laboratorio Digital A - Experiencia 4
--
-- Functional description of 4-bit binary counter on VHDL 
-- 
-- Author: Lucas Penna Saraiva and Stefan R. Raposo
-- 
-- >> Design requirements:
-- 
-- The Clear signal is asynchronous
-- The Load signal is syncrhonous
-- Enable signal

library ieee;
use ieee.numeric_bit.all;

entity Decade_Counter is

	Port ( Clear          : in bit;
			 Clock          : in bit;
			 Load           : in bit;
			 Enable         : in bit;
			 Up             : in bit; -- 'UP = 1 // Down = 0'
			 Counter_Input  : in bit_vector (3 downto 0);
			 RCO            : out bit;
			 Counter_Output : out bit_vector (3 downto 0));

end Decade_Counter;

architecture Behaviour of Decade_Counter is

	signal Count : unsigned(3 downto 0);

	begin
	
	-- Process Count
	
	process(Clock, Count)
	begin	

	if Clear = '1' then
		Count <= "0000";
		
	-- Up counter
	elsif rising_edge(Clock) and Enable ='1' then
	
		-- Verifying the count initial condition
		
		if Load = '1' then
		
			Count <= unsigned(Counter_Input);
			
		else
		
		-- Up counting
		
			if Up = '1' then
			
				if Count = "1000" then
				
				Count <= Count + 1;
				RCO <= '1';
					
				else
				
					RCO <= '0';
					Count <= Count + 1;
				
				end if;
			
			  if Count = "1001" then
				Count <= "0000";
			  end if;
			  
				
			-- Down Counting
			
			else
			
				if Count = "0001" then
					
				
					Count <= Count - 1;
					RCO <= '1';
				
				else
				
					Count <= Count - 1;
					RCO <= '0';
				
				end if;
				
				if Count = "0000" then
				Count <= "1001";
			  end if;

					
				end if;
			end if;
		end if;

	
	end process;
		
	Counter_Output <= bit_vector(Count);
		
end Behaviour;

Practica_3_codigo_VHDL/updown_tb.vhdl
library ieee;
use ieee.numeric_bit.all;

entity Decade_Counter_tb is
end Decade_Counter_tb;

architecture behaviour of Decade_Counter_tb is

	component Decade_Counter is
		port(Clear          : in bit;
			 Clock          : in bit;
			 Load           : in bit;
			 Enable         : in bit;
			 Up             : in bit; -- 'UP = 1 // Down = 0'
			 Counter_Input  : in bit_vector (3 downto 0);
			 RCO            : out bit;
			 Counter_Output : out bit_vector (3 downto 0));
	end component Decade_Counter;
	
	signal Clk : bit := '0';
	signal rst : bit := '0';
	signal enable : bit := '1';
	signal load : bit := '0';
	signal UPDN, rco : bit;
	signal cout, cin : bit_vector(3 downto 0);
	
	constant clk_period : time := 10 ns;
	
	begin
	
	UpDown: Decade_Counter port map(Clear => rst, Clock => Clk, Load => load, Enable => enable, Up => UPDN, Counter_Input => cin, RCO => rco, Counter_Output => cout);
	
	clk_process :process
	begin
	clk <= '0';
	wait for clk_period/2;
	clk <= '1';
	wait for clk_period/2;
	end process;
	
	startup : process
	begin
	
	rst <= '1';
	wait for 5 ns;
	
	rst <= '0';
	wait for 100 ms;
	
	end process;
	
	upydown : process
	begin
	
	UPDN <= '1';
	WAIT for 200 ns;
	
	UPDN <= '0';
	wait for 200 ns;
	
	end process;
	
end architecture;

Practica_3_codigo_VHDL/updown_tb.vcd
$date
  Sat Mar 28 02:57:02 2020
$end
$version
  GHDL v0
$end
$timescale
  1 fs
$end
$scope module standard $end
$upscope $end
$scope module numeric_bit $end
$upscope $end
$scope module decade_counter_tb $end
$var reg 1 ! clk $end
$var reg 1 " rst $end
$var reg 1 # enable $end
$var reg 1 $ load $end
$var reg 1 % updn $end
$var reg 1 & rco $end
$var reg 4 ' cout[3:0] $end
$var reg 4 ( cin[3:0] $end
$scope module updown $end
$var reg 1 ) clear $end
$var reg 1 * clock $end
$var reg 1 + load $end
$var reg 1 , enable $end
$var reg 1 - up $end
$var reg 4 . counter_input[3:0] $end
$var reg 1 / rco $end
$var reg 4 0 counter_output[3:0] $end
$var reg 4 1 count[3:0] $end
$upscope $end
$upscope $end
$enddefinitions $end
#0
0!
1"
1#
0$
1%
0&
b0000 '
b0000 (
1)
0*
0+
1,
1-
b0000 .
0/
b0000 0
b0000 1
#5000000
1!
0"
b0001 '
0)
1*
b0001 0
b0001 1
#10000000
0!
0*
#15000000
1!
b0010 '
1*
b0010 0
b0010 1
#20000000
0!
0*
#25000000
1!
b0011 '
1*
b0011 0
b0011 1
#30000000
0!
0*
#35000000
1!
b0100 '
1*
b0100 0
b0100 1
#40000000
0!
0*
#45000000
1!
b0101 '
1*
b0101 0
b0101 1
#50000000
0!
0*
#55000000
1!
b0110 '
1*
b0110 0
b0110 1
#60000000
0!
0*
#65000000
1!
b0111 '
1*
b0111 0
b0111 1
#70000000
0!
0*
#75000000
1!
b1000 '
1*
b1000 0
b1000 1
#80000000
0!
0*
#85000000
1!
1&
b1001 '
1*
1/
b1001 0
b1001 1
#90000000
0!
0*
#95000000
1!
0&
b0000 '
1*
0/
b0000 0
b0000 1
#100000000
0!
0*
#105000000
1!
b0001 '
1*
b0001 0
b0001 1
#110000000
0!
0*
#115000000
1!
b0010 '
1*
b0010 0
b0010 1
#120000000
0!
0*
#125000000
1!
b0011 '
1*
b0011 0
b0011 1
#130000000
0!
0*
#135000000
1!
b0100 '
1*
b0100 0
b0100 1
#140000000
0!
0*
#145000000
1!
b0101 '
1*
b0101 0
b0101 1
#150000000
0!
0*
#155000000
1!
b0110 '
1*
b0110 0
b0110 1
#160000000
0!
0*
#165000000
1!
b0111 '
1*
b0111 0
b0111 1
#170000000
0!
0*
#175000000
1!
b1000 '
1*
b1000 0
b1000 1
#180000000
0!
0*
#185000000
1!
1&
b1001 '
1*
1/
b1001 0
b1001 1
#190000000
0!
0*
#195000000
1!
0&
b0000 '
1*
0/
b0000 0
b0000 1
#200000000
0!
0%
0*
0-
#205000000
1!
b1001 '
1*
b1001 0
b1001 1
#210000000
0!
0*
#215000000
1!
b1000 '
1*
b1000 0
b1000 1
#220000000
0!
0*
#225000000
1!
b0111 '
1*
b0111 0
b0111 1
#230000000
0!
0*
#235000000
1!
b0110 '
1*
b0110 0
b0110 1
#240000000
0!
0*
#245000000
1!
b0101 '
1*
b0101 0
b0101 1
#250000000
0!
0*
#255000000
1!
b0100 '
1*
b0100 0
b0100 1
#260000000
0!
0*
#265000000
1!
b0011 '
1*
b0011 0
b0011 1
#270000000
0!
0*
#275000000
1!
b0010 '
1*
b0010 0
b0010 1
#280000000
0!
0*
#285000000
1!
b0001 '
1*
b0001 0
b0001 1
#290000000
0!
0*
#295000000
1!
1&
b0000 '
1*
1/
b0000 0
b0000 1
#300000000
0!
0*
#305000000
1!
0&
b1001 '
1*
0/
b1001 0
b1001 1
#310000000
0!
0*
#315000000
1!
b1000 '
1*
b1000 0
b1000 1
#320000000
0!
0*
#325000000
1!
b0111 '
1*
b0111 0
b0111 1
#330000000
0!
0*
#335000000
1!
b0110 '
1*
b0110 0
b0110 1
#340000000
0!
0*
#345000000
1!
b0101 '
1*
b0101 0
b0101 1
#350000000
0!
0*
#355000000
1!
b0100 '
1*
b0100 0
b0100 1
#360000000
0!
0*
#365000000
1!
b0011 '
1*
b0011 0
b0011 1
#370000000
0!
0*
#375000000
1!
b0010 '
1*
b0010 0
b0010 1
#380000000
0!
0*
#385000000
1!
b0001 '
1*
b0001 0
b0001 1
#390000000
0!
0*
#395000000
1!
1&
b0000 '
1*
1/
b0000 0
b0000 1
#400000000
0!
1%
0*
1-
#405000000
1!
0&
b0001 '
1*
0/
b0001 0
b0001 1
#410000000
0!
0*
#415000000
1!
b0010 '
1*
b0010 0
b0010 1
#420000000
0!
0*
#425000000
1!
b0011 '
1*
b0011 0
b0011 1
#430000000
0!
0*
#435000000
1!
b0100 '
1*
b0100 0
b0100 1
#440000000
0!
0*
#445000000
1!
b0101 '
1*
b0101 0
b0101 1
#450000000
0!
0*
#455000000
1!
b0110 '
1*
b0110 0
b0110 1
#460000000
0!
0*
#465000000
1!
b0111 '
1*
b0111 0
b0111 1
#470000000
0!
0*
#475000000
1!
b1000 '
1*
b1000 0
b1000 1
#480000000
0!
0*
#485000000
1!
1&
b1001 '
1*
1/
b1001 0
b1001 1
#490000000
0!
0*
#495000000
1!
0&
b0000 '
1*
0/
b0000 0
b0000 1
#500000000
0!
0*
#505000000
1!
b0001 '
1*
b0001 0
b0001 1
#510000000
0!
0*
#515000000
1!
b0010 '
1*
b0010 0
b0010 1
#520000000
0!
0*
#525000000
1!
b0011 '
1*
b0011 0
b0011 1
#530000000
0!
0*
#535000000
1!
b0100 '
1*
b0100 0
b0100 1
#540000000
0!
0*
#545000000
1!
b0101 '
1*
b0101 0
b0101 1
#550000000
0!
0*
#555000000
1!
b0110 '
1*
b0110 0
b0110 1
#560000000
0!
0*
#565000000
1!
b0111 '
1*
b0111 0
b0111 1
#570000000
0!
0*
#575000000
1!
b1000 '
1*
b1000 0
b1000 1
#580000000
0!
0*
#585000000
1!
1&
b1001 '
1*
1/
b1001 0
b1001 1
#590000000
0!
0*
#595000000
1!
0&
b0000 '
1*
0/
b0000 0
b0000 1
#600000000
0!
0%
0*
0-
#605000000
1!
b1001 '
1*
b1001 0
b1001 1
#610000000
0!
0*
#615000000
1!
b1000 '
1*
b1000 0
b1000 1
#620000000
0!
0*
#625000000
1!
b0111 '
1*
b0111 0
b0111 1
#630000000
0!
0*
#635000000
1!
b0110 '
1*
b0110 0
b0110 1
#640000000
0!
0*
#645000000
1!
b0101 '
1*
b0101 0
b0101 1
#650000000
0!
0*
#655000000
1!
b0100 '
1*
b0100 0
b0100 1
#660000000
0!
0*
#665000000
1!
b0011 '
1*
b0011 0
b0011 1
#670000000
0!
0*
#675000000
1!
b0010 '
1*
b0010 0
b0010 1
#680000000
0!
0*
#685000000
1!
b0001 '
1*
b0001 0
b0001 1
#690000000
0!
0*
#695000000
1!
1&
b0000 '
1*
1/
b0000 0
b0000 1
#700000000
0!
0*
#705000000
1!
0&
b1001 '
1*
0/
b1001 0
b1001 1
#710000000
0!
0*
#715000000
1!
b1000 '
1*
b1000 0
b1000 1
#720000000
0!
0*
#725000000
1!
b0111 '
1*
b0111 0
b0111 1
#730000000
0!
0*
#735000000
1!
b0110 '
1*
b0110 0
b0110 1
#740000000
0!
0*
#745000000
1!
b0101 '
1*
b0101 0
b0101 1
#750000000
0!
0*
#755000000
1!
b0100 '
1*
b0100 0
b0100 1
#760000000
0!
0*
#765000000
1!
b0011 '
1*
b0011 0
b0011 1
#770000000
0!
0*
#775000000
1!
b0010 '
1*
b0010 0
b0010 1
#780000000
0!
0*
#785000000
1!
b0001 '
1*
b0001 0
b0001 1
#790000000
0!
0*
#795000000
1!
1&
b0000 '
1*
1/
b0000 0
b0000 1
#800000000
0!
1%
0*
1-
