Registro-Corrimiento-8bits/shift74194.vhdl
library ieee;
use ieee.std_logic_1164.all;

entity shift74194 is
    port (
        clr, clk, sdr, sdl : in std_logic;
        mode : in std_logic_vector(1 downto 0);
        parallel : in std_logic_vector(3 downto 0);
        q : inout std_logic_vector(3 downto 0)
    );
end entity;

architecture arch of shift74194 is

begin
    process(clr, clk, mode)
        variable q_helper : std_logic_vector(3 downto 0);
    begin
        if clr = '0' then
            q <= "0000";
        else
            if rising_edge(clk) then
                case mode is
                    when "00" =>
                        q_helper := q_helper;
                    when "01" =>
                        q_helper(3) := q_helper(2);
                        q_helper(2) := q_helper(1);
                        q_helper(1) := q_helper(0);
                        q_helper(0) := sdr;
                    when "10" =>
                        q_helper(3) := sdl;
                        q_helper(2) := q_helper(3);
                        q_helper(1) := q_helper(2);
                        q_helper(0) := q_helper(1);
                    when "11" =>
                        q_helper := parallel;
                    when others =>
                        null;
                end case;
                q <= q_helper;
            end if;
        end if;
    end process;

end arch ; -- arch

Registro-Corrimiento-8bits/shift74194_tb.vhdl
library ieee;
use ieee.std_logic_1164.all;

entity shift74194_tb is
end entity;


architecture arch of shift74194_tb is
    
    component shift74194 is
        port (
            clr, clk, sdr, sdl : in std_logic;
            mode : in std_logic_vector(1 downto 0);
            parallel : in std_logic_vector(3 downto 0);
            q : out std_logic_vector(3 downto 0)
        );
    end component;

    signal clr, clk, sdr, sdl : std_logic;
    signal mode : std_logic_vector(1 downto 0);
    signal parallel, q : std_logic_vector(3 downto 0);

    constant period : time := 10 ns;

begin

    UTT : shift74194 port map (clr, clk, sdr, sdl, mode, parallel, q);

    clk_process : process
    begin
        clk <= '0';
        wait for period/2;
        clk <= '1';
        wait for period/2;
    end process;

    clr <= '0', '1' after period*4, '0' after period*20;
    mode <= "00", "11" after period*5, "10" after period*6, "01" after period*12, "00" after period*16;
    parallel <= "1010";
    sdr <= '0';
    sdl <= '1';

   

end arch ;

Registro-Corrimiento-8bits/shift74194_tb.vcd
$date
  Fri May 08 14:50:50 2020
$end
$version
  GHDL v0
$end
$timescale
  1 fs
$end
$scope module standard $end
$upscope $end
$scope module std_logic_1164 $end
$upscope $end
$scope module shift74194_tb $end
$var reg 1 ! clr $end
$var reg 1 " clk $end
$var reg 1 # sdr $end
$var reg 1 $ sdl $end
$var reg 2 % mode[1:0] $end
$var reg 4 & parallel[3:0] $end
$var reg 4 ' q[3:0] $end
$scope module utt $end
$var reg 1 ( clr $end
$var reg 1 ) clk $end
$var reg 1 * sdr $end
$var reg 1 + sdl $end
$var reg 2 , mode[1:0] $end
$var reg 4 - parallel[3:0] $end
$var reg 4 . q[3:0] $end
$upscope $end
$upscope $end
$enddefinitions $end
#0
0!
0"
0#
1$
b00 %
b1010 &
b0000 '
0(
0)
0*
1+
b00 ,
b1010 -
b0000 .
#5000000
1"
1)
#10000000
0"
0)
#15000000
1"
1)
#20000000
0"
0)
#25000000
1"
1)
#30000000
0"
0)
#35000000
1"
1)
#40000000
1!
0"
1(
0)
#45000000
1"
bUUUU '
1)
bUUUU .
#50000000
0"
b11 %
0)
b11 ,
#55000000
1"
b1010 '
1)
b1010 .
#60000000
0"
b10 %
0)
b10 ,
#65000000
1"
b1111 '
1)
b1111 .
#70000000
0"
0)
#75000000
1"
1)
#80000000
0"
0)
#85000000
1"
1)
#90000000
0"
0)
#95000000
1"
1)
#100000000
0"
0)
#105000000
1"
1)
#110000000
0"
0)
#115000000
1"
1)
#120000000
0"
b01 %
0)
b01 ,
#125000000
1"
b1110 '
1)
b1110 .
#130000000
0"
0)
#135000000
1"
b1100 '
1)
b1100 .
#140000000
0"
0)
#145000000
1"
b1000 '
1)
b1000 .
#150000000
0"
0)
#155000000
1"
b0000 '
1)
b0000 .
#160000000
0"
b00 %
0)
b00 ,
#165000000
1"
1)
#170000000
0"
0)
#175000000
1"
1)
#180000000
0"
0)
#185000000
1"
1)
#190000000
0"
0)
#195000000
1"
1)
#200000000
0!
0"
0(
0)
