Registro-Corrimiento-8bits/shift74194.vhdl
library ieee;
use ieee.std_logic_1164.all;

entity shift74194 is
    port (
        clr, clk, sdr, sdl : in std_logic;
        mode : in std_logic_vector(1 downto 0);
        parallel : in std_logic_vector(3 downto 0);
        q : inout std_logic_vector(3 downto 0)
    );
end entity;

architecture arch of shift74194 is

begin
    process(clr, clk, mode)
        variable q_helper : std_logic_vector(3 downto 0);
    begin
        if clr = '0' then
            q <= "0000";
        else
            if rising_edge(clk) then
                case mode is
                    when "00" =>
                        q_helper := q_helper;
                    when "01" =>
                        q_helper(3) := q_helper(2);
                        q_helper(2) := q_helper(1);
                        q_helper(1) := q_helper(0);
                        q_helper(0) := sdr;
                    when "10" =>
                        q_helper(3) := sdl;
                        q_helper(2) := q_helper(3);
                        q_helper(1) := q_helper(2);
                        q_helper(0) := q_helper(1);
                    when "11" =>
                        q_helper := parallel;
                    when others =>
                        null;
                end case;
                q <= q_helper;
            end if;
        end if;
    end process;

end arch ; -- arch

Registro-Corrimiento-8bits/shift_register_8bits.vhdl
library ieee;
use ieee.std_logic_1164.all;
use ieee.numeric_std.all;
entity shift_register_8bits is
    port(
        x: in std_logic_vector(7 downto 0);
        s: in std_logic_vector(1 downto 0);
        rsd,lsd,clrb,clk: in std_logic;
        y: inout std_logic_vector(7 downto 0)
    );
end shift_register_8bits;
architecture test of shift_register_8bits is
    component shift74194 is
        port(
            clr, clk, sdr, sdl : in std_logic;
            mode : in std_logic_vector(1 downto 0);
            parallel : in std_logic_vector(3 downto 0);
            q : inout std_logic_vector(3 downto 0)
        );
    end component;
begin
    S0: shift74194 port map(clrb, clk, y(4), lsd, s, x(3 downto 0), y(3 downto 0));
    S1: shift74194 port map(clrb, clk, rsd, y(3), s, x(7 downto 4), y(7 downto 4));
end test;

Registro-Corrimiento-8bits/shift_register_8bits_tb.vhdl
library IEEE;
use IEEE.Std_logic_1164.all;
use IEEE.Numeric_Std.all;

entity shift_register_8bits_tb is
end;

architecture bench of shift_register_8bits_tb is

  component shift_register_8bits
      port(
        x: in std_logic_vector(7 downto 0);
        s: in std_logic_vector(1 downto 0);
        rsd,lsd,clrb,clk: in std_logic;
        y: inout std_logic_vector(7 downto 0)
      );
  end component;

  signal x: std_logic_vector(7 downto 0);
  signal s: std_logic_vector(1 downto 0);
  signal rsd,lsd,clrb,clk:  std_logic;
  signal y: std_logic_vector(7 downto 0);
  constant period : time := 10 ns;

begin

  uut: shift_register_8bits port map ( x    => x,
                                       s    => s,
                                       rsd  => rsd,
                                       lsd  => lsd,
                                       clrb => clrb,
                                       clk  => clk,
                                       y    => y );

  clk_process : process
  begin
    clk <= '0';
    wait for period/2;
    clk <= '1';
    wait for period/2;
  end process;                                
  clrb <= '0', '1' after period*4, '0' after period*20;
  s <= "00", "11" after period*5, "10" after period*6, "01" after period*12, "00" after period*16;
  x <= "10101011";
  rsd <= '0';
  lsd <= '1';
end bench;

Registro-Corrimiento-8bits/shift8bits.vcd
$date
  Mon May 11 23:30:28 2020
$end
$version
  GHDL v0
$end
$timescale
  1 fs
$end
$scope module standard $end
$upscope $end
$scope module std_logic_1164 $end
$upscope $end
$scope module numeric_std $end
$upscope $end
$scope module shift_register_8bits_tb $end
$var reg 8 ! x[7:0] $end
$var reg 2 " s[1:0] $end
$var reg 1 # rsd $end
$var reg 1 $ lsd $end
$var reg 1 % clrb $end
$var reg 1 & clk $end
$var reg 8 ' y[7:0] $end
$scope module uut $end
$var reg 8 ( x[7:0] $end
$var reg 2 ) s[1:0] $end
$var reg 1 * rsd $end
$var reg 1 + lsd $end
$var reg 1 , clrb $end
$var reg 1 - clk $end
$var reg 8 . y[7:0] $end
$scope module s0 $end
$var reg 1 / clr $end
$var reg 1 0 clk $end
$var reg 1 1 sdr $end
$var reg 1 2 sdl $end
$var reg 2 3 mode[1:0] $end
$var reg 4 4 parallel[3:0] $end
$var reg 4 5 q[3:0] $end
$upscope $end
$scope module s1 $end
$var reg 1 6 clr $end
$var reg 1 7 clk $end
$var reg 1 8 sdr $end
$var reg 1 9 sdl $end
$var reg 2 : mode[1:0] $end
$var reg 4 ; parallel[3:0] $end
$var reg 4 < q[3:0] $end
$upscope $end
$upscope $end
$upscope $end
$enddefinitions $end
#0
b10101011 !
b00 "
0#
1$
0%
0&
b00000000 '
b10101011 (
b00 )
0*
1+
0,
0-
b00000000 .
0/
00
01
12
b00 3
b1011 4
b0000 5
06
07
08
09
b00 :
b1010 ;
b0000 <
#5000000
1&
1-
10
17
#10000000
0&
0-
00
07
#15000000
1&
1-
10
17
#20000000
0&
0-
00
07
#25000000
1&
1-
10
17
#30000000
0&
0-
00
07
#35000000
1&
1-
10
17
#40000000
1%
0&
1,
0-
1/
00
16
07
#45000000
1&
bUUUUUUUU '
1-
bUUUUUUUU .
10
U1
bUUUU 5
17
U9
bUUUU <
#50000000
b11 "
0&
b11 )
0-
00
b11 3
07
b11 :
#55000000
1&
b10101011 '
1-
b10101011 .
10
01
b1011 5
17
19
b1010 <
#60000000
b10 "
0&
b10 )
0-
00
b10 3
07
b10 :
#65000000
1&
b11111111 '
1-
b11111111 .
10
11
b1111 5
17
b1111 <
#70000000
0&
0-
00
07
#75000000
1&
1-
10
17
#80000000
0&
0-
00
07
#85000000
1&
1-
10
17
#90000000
0&
0-
00
07
#95000000
1&
1-
10
17
#100000000
0&
0-
00
07
#105000000
1&
1-
10
17
#110000000
0&
0-
00
07
#115000000
1&
1-
10
17
#120000000
b01 "
0&
b01 )
0-
00
b01 3
07
b01 :
#125000000
1&
b11101111 '
1-
b11101111 .
10
01
17
b1110 <
#130000000
0&
0-
00
07
#135000000
1&
b11001110 '
1-
b11001110 .
10
b1110 5
17
b1100 <
#140000000
0&
0-
00
07
#145000000
1&
b10001100 '
1-
b10001100 .
10
b1100 5
17
b1000 <
