Practica_4_simulacion/7segment_decoder.vhdl
library IEEE;
use IEEE.STD_LOGIC_1164.ALL;
 
entity bcd_7segment is
Port ( BCDin : in STD_LOGIC_VECTOR (3 downto 0);
Seven_Segment : out STD_LOGIC_VECTOR (6 downto 0));
end bcd_7segment;
 
architecture Behavioral of bcd_7segment is
 
begin
 
process(BCDin)
begin
 
case BCDin is
when "0000" =>
Seven_Segment <= "0000001"; ---0
when "0001" =>
Seven_Segment <= "1001111"; ---1
when "0010" =>
Seven_Segment <= "0010010"; ---2
when "0011" =>
Seven_Segment <= "0000110"; ---3
when "0100" =>
Seven_Segment <= "1001100"; ---4
when "0101" =>
Seven_Segment <= "0100100"; ---5
when "0110" =>
Seven_Segment <= "0100000"; ---6
when "0111" =>
Seven_Segment <= "0001111"; ---7
when "1000" =>
Seven_Segment <= "0000000"; ---8
when "1001" =>
Seven_Segment <= "0000100"; ---9
when others =>
Seven_Segment <= "1111111"; ---null
end case;
 
end process;
 
end Behavioral;

Practica_4_codigo_VHDL/7segment_decodertb.vhdl
LIBRARY ieee;
USE ieee.std_logic_1164.ALL;
 
ENTITY tb_bcd_7seg IS
END tb_bcd_7seg;
 
ARCHITECTURE behavior OF tb_bcd_7seg IS
 
-- Component Declaration for the Unit Under Test (UUT)
 
COMPONENT bcd_7segment
PORT(
BCDin : IN std_logic_vector(3 downto 0);
Seven_Segment : OUT std_logic_vector(6 downto 0)
);
END COMPONENT;
 
--Inputs
signal BCDin : std_logic_vector(3 downto 0) := (others => '0');
 
--Outputs
signal Seven_Segment : std_logic_vector(6 downto 0);
 
BEGIN
 
-- Instantiate the Unit Under Test (UUT)
uut: bcd_7segment PORT MAP (
BCDin => BCDin,
Seven_Segment => Seven_Segment
);
 
-- Stimulus process
stim_proc: process
begin
 
BCDin <= "0000";
wait for 100 ns;
BCDin <= "0001";
wait for 100 ns;
BCDin <= "0010";
wait for 100 ns;
BCDin <= "0011";
wait for 100 ns;
BCDin <= "0100";
wait for 100 ns;
BCDin <= "0101";
wait for 100 ns;
BCDin <= "0110";
wait for 100 ns;
BCDin <= "0111";
wait for 100 ns;
BCDin <= "1000";
wait for 100 ns;
BCDin <= "1001";
wait for 100 ns;
end process;
 
END;

Practica_4_codigo_VHDL/bcd_7seg.vcd
$date
  Tue Mar 24 18:57:40 2020
$end
$version
  GHDL v0
$end
$timescale
  1 fs
$end
$scope module standard $end
$upscope $end
$scope module std_logic_1164 $end
$upscope $end
$scope module tb_bcd_7seg $end
$var reg 4 ! bcdin[3:0] $end
$var reg 7 " seven_segment[6:0] $end
$scope module uut $end
$var reg 4 # bcdin[3:0] $end
$var reg 7 $ seven_segment[6:0] $end
$upscope $end
$upscope $end
$enddefinitions $end
#0
b0000 !
b0000001 "
b0000 #
b0000001 $
#100000000
b0001 !
b1001111 "
b0001 #
b1001111 $
#200000000
b0010 !
b0010010 "
b0010 #
b0010010 $
#300000000
b0011 !
b0000110 "
b0011 #
b0000110 $
#400000000
b0100 !
b1001100 "
b0100 #
b1001100 $
#500000000
b0101 !
b0100100 "
b0101 #
b0100100 $
#600000000
b0110 !
b0100000 "
b0110 #
b0100000 $
#700000000
b0111 !
b0001111 "
b0111 #
b0001111 $
#800000000
b1000 !
b0000000 "
b1000 #
b0000000 $
#900000000
b1001 !
b0000100 "
b1001 #
b0000100 $
#1000000000
b0000 !
b0000001 "
b0000 #
b0000001 $
