Practica_5_codigo_VHDL/DecadeCounter.vhdl
library ieee;
use ieee.std_logic_1164.all;
use ieee.numeric_std.all;
entity mod10_counter is
   port(
      clk, reset: in std_logic;
      q: out std_logic_vector(3 downto 0);
      en: out std_logic
   );
end mod10_counter;

architecture two_seg_arch of mod10_counter is
   constant TEN: integer := 10;
   signal r_reg: unsigned(3 downto 0);
   signal r_next: unsigned(3 downto 0);
   signal en1: std_logic;
begin
   -- register
   process(clk,reset)
   begin
      if (reset='1') then
         r_reg <= (others=>'0');
      elsif (clk'event and clk='1') then
         r_reg <= r_next;
      end if;
      if (r_reg = "1001") then
         en1 <= '1';
         else
            en1 <= '0';
      end if;
   end process;
   -- next-state logic
   r_next <= (others=>'0') when r_reg=(TEN-1) else
             r_reg + 1;

   -- output logic
   q <= std_logic_vector(r_reg);
   en <= en1;
end two_seg_arch;

Practica_5_codigo_VHDL/DecadeCounter_tb.vhdl
library IEEE;
use IEEE.Std_logic_1164.all;
use IEEE.Numeric_Std.all;

entity mod10_counter_tb is
end;

architecture bench of mod10_counter_tb is

  component mod10_counter
     port(
        clk, reset: in std_logic;
        q: out std_logic_vector(3 downto 0);
        en: out std_logic
     );
  end component;

  signal clk, reset: std_logic;
  signal q: std_logic_vector(3 downto 0);
  signal en: std_logic ;

  constant clock_period: time := 1 ns;
  signal stop_the_clock: boolean;

begin

  uut: mod10_counter port map ( clk   => clk,
                                reset => reset,
                                q     => q,
                                en    => en );

  stimulus: process
  begin
  
    -- Put initialisation code here
    reset <= '1';
    wait for 1 ns;
    
    reset <= '0';
    wait for 60 ns;

    -- Put test bench stimulus code here

    stop_the_clock <= true;
    wait;
  end process;

  clocking: process
  begin
    while not stop_the_clock loop
      clk <= '0', '1' after clock_period / 2;
      wait for clock_period;
    end loop;
    wait;
  end process;

end;

Practica_5_codigo_VHDL/DecadeCounter_tb.vcd
$date
  Fri Apr 17 14:26:09 2020
$end
$version
  GHDL v0
$end
$timescale
  1 fs
$end
$scope module standard $end
$upscope $end
$scope module std_logic_1164 $end
$upscope $end
$scope module numeric_std $end
$upscope $end
$scope module mod10_counter_tb $end
$var reg 1 ! clk $end
$var reg 1 " reset $end
$var reg 4 # q[3:0] $end
$var reg 1 $ en $end
$var reg 1 % stop_the_clock $end
$scope module uut $end
$var reg 1 & clk $end
$var reg 1 ' reset $end
$var reg 4 ( q[3:0] $end
$var reg 1 ) en $end
$var reg 4 * r_reg[3:0] $end
$var reg 4 + r_next[3:0] $end
$var reg 1 , en1 $end
$upscope $end
$upscope $end
$enddefinitions $end
#0
0!
1"
b0000 #
0$
0%
0&
1'
b0000 (
0)
b0000 *
b0001 +
0,
#500000
1!
1&
#1000000
0!
0"
0&
0'
#1500000
1!
b0001 #
1&
b0001 (
b0001 *
b0010 +
#2000000
0!
0&
#2500000
1!
b0010 #
1&
b0010 (
b0010 *
b0011 +
#3000000
0!
0&
#3500000
1!
b0011 #
1&
b0011 (
b0011 *
b0100 +
#4000000
0!
0&
#4500000
1!
b0100 #
1&
b0100 (
b0100 *
b0101 +
#5000000
0!
0&
#5500000
1!
b0101 #
1&
b0101 (
b0101 *
b0110 +
#6000000
0!
0&
#6500000
1!
b0110 #
1&
b0110 (
b0110 *
b0111 +
#7000000
0!
0&
#7500000
1!
b0111 #
1&
b0111 (
b0111 *
b1000 +
#8000000
0!
0&
#8500000
1!
b1000 #
1&
b1000 (
b1000 *
b1001 +
#9000000
0!
0&
#9500000
1!
b1001 #
1&
b1001 (
b1001 *
b0000 +
#10000000
0!
1$
0&
1)
1,
#10500000
1!
b0000 #
1&
b0000 (
b0000 *
b0001 +
#11000000
0!
0$
0&
0)
0,
#11500000
1!
b0001 #
1&
b0001 (
b0001 *
b0010 +
#12000000
0!
0&
#12500000
1!
b0010 #
1&
b0010 (
b0010 *
b0011 +
#13000000
0!
0&
#13500000
1!
b0011 #
1&
b0011 (
b0011 *
b0100 +
#14000000
0!
0&
#14500000
1!
b0100 #
1&
b0100 (
b0100 *
b0101 +
#15000000
0!
0&
#15500000
1!
b0101 #
1&
b0101 (
b0101 *
b0110 +
#16000000
0!
0&
#16500000
1!
b0110 #
1&
b0110 (
b0110 *
b0111 +
#17000000
0!
0&
#17500000
1!
b0111 #
1&
b0111 (
b0111 *
b1000 +
#18000000
0!
0&
#18500000
1!
b1000 #
1&
b1000 (
b1000 *
b1001 +
#19000000
0!
0&
#19500000
1!
b1001 #
1&
b1001 (
b1001 *
b0000 +
#20000000
0!
1$
0&
1)
1,
#20500000
1!
b0000 #
1&
b0000 (
b0000 *
b0001 +
#21000000
0!
0$
0&
0)
0,
#21500000
1!
b0001 #
1&
b0001 (
b0001 *
b0010 +
#22000000
0!
0&
#22500000
1!
b0010 #
1&
b0010 (
b0010 *
b0011 +
#23000000
0!
0&
#23500000
1!
b0011 #
1&
b0011 (
b0011 *
b0100 +
#24000000
0!
0&
#24500000
1!
b0100 #
1&
b0100 (
b0100 *
b0101 +
#25000000
0!
0&
#25500000
1!
b0101 #
1&
b0101 (
b0101 *
b0110 +
#26000000
0!
0&
#26500000
1!
b0110 #
1&
b0110 (
b0110 *
b0111 +
#27000000
0!
0&
#27500000
1!
b0111 #
1&
b0111 (
b0111 *
b1000 +
#28000000
0!
0&
#28500000
1!
b1000 #
1&
b1000 (
b1000 *
b1001 +
#29000000
0!
0&
#29500000
1!
b1001 #
1&
b1001 (
b1001 *
b0000 +
#30000000
0!
1$
0&
1)
1,
#30500000
1!
b0000 #
1&
b0000 (
b0000 *
b0001 +
#31000000
0!
0$
0&
0)
0,
#31500000
1!
b0001 #
1&
b0001 (
b0001 *
b0010 +
#32000000
0!
0&
#32500000
1!
b0010 #
1&
b0010 (
b0010 *
b0011 +
#33000000
0!
0&
#33500000
1!
b0011 #
1&
b0011 (
b0011 *
b0100 +
#34000000
0!
0&
#34500000
1!
b0100 #
1&
b0100 (
b0100 *
b0101 +
#35000000
0!
0&
#35500000
1!
b0101 #
1&
b0101 (
b0101 *
b0110 +
#36000000
0!
0&
#36500000
1!
b0110 #
1&
b0110 (
b0110 *
b0111 +
#37000000
0!
0&
#37500000
1!
b0111 #
1&
b0111 (
b0111 *
b1000 +
#38000000
0!
0&
#38500000
1!
b1000 #
1&
b1000 (
b1000 *
b1001 +
#39000000
0!
0&
#39500000
1!
b1001 #
1&
b1001 (
b1001 *
b0000 +
#40000000
0!
1$
0&
1)
1,
#40500000
1!
b0000 #
1&
b0000 (
b0000 *
b0001 +
#41000000
0!
0$
0&
0)
0,
#41500000
1!
b0001 #
1&
b0001 (
b0001 *
b0010 +
#42000000
0!
0&
#42500000
1!
b0010 #
1&
b0010 (
b0010 *
b0011 +
#43000000
0!
0&
#43500000
1!
b0011 #
1&
b0011 (
b0011 *
b0100 +
#44000000
0!
0&
#44500000
1!
b0100 #
1&
b0100 (
b0100 *
b0101 +
#45000000
0!
0&
#45500000
1!
b0101 #
1&
b0101 (
b0101 *
b0110 +
#46000000
0!
0&
#46500000
1!
b0110 #
1&
b0110 (
b0110 *
b0111 +
#47000000
0!
0&
#47500000
1!
b0111 #
1&
b0111 (
b0111 *
b1000 +
#48000000
0!
0&
#48500000
1!
b1000 #
1&
b1000 (
b1000 *
b1001 +
#49000000
0!
0&
#49500000
1!
b1001 #
1&
b1001 (
b1001 *
b0000 +
#50000000
0!
1$
0&
1)
1,
#50500000
1!
b0000 #
1&
b0000 (
b0000 *
b0001 +
#51000000
0!
0$
0&
0)
0,
#51500000
1!
b0001 #
1&
b0001 (
b0001 *
b0010 +
#52000000
0!
0&
#52500000
1!
b0010 #
1&
b0010 (
b0010 *
b0011 +
#53000000
0!
0&
#53500000
1!
b0011 #
1&
b0011 (
b0011 *
b0100 +
#54000000
0!
0&
#54500000
1!
b0100 #
1&
b0100 (
b0100 *
b0101 +
#55000000
0!
0&
#55500000
1!
b0101 #
1&
b0101 (
b0101 *
b0110 +
#56000000
0!
0&
#56500000
1!
b0110 #
1&
b0110 (
b0110 *
b0111 +
#57000000
0!
0&
#57500000
1!
b0111 #
1&
b0111 (
b0111 *
b1000 +
#58000000
0!
0&
#58500000
1!
b1000 #
1&
b1000 (
b1000 *
b1001 +
#59000000
0!
0&
#59500000
1!
b1001 #
1&
b1001 (
b1001 *
b0000 +
#60000000
0!
1$
0&
1)
1,
#60500000
1!
b0000 #
1&
b0000 (
b0000 *
b0001 +
#61000000
0!
0$
1%
0&
0)
0,
#61500000
1!
b0001 #
1&
b0001 (
b0001 *
b0010 +
