Practica_5_codigo_VHDL/ThirteenCounter.vhdl
library ieee;
use ieee.std_logic_1164.all;
use ieee.numeric_std.all;
entity mod13_counter is
   port(
      clk, reset: in std_logic;
      en: out std_logic;
      q: out std_logic_vector(3 downto 0)
   );
end mod13_counter;

architecture two_seg_arch of mod13_counter is
   constant SIX: integer := 13;
   signal r_reg: unsigned(3 downto 0);
   signal r_next: unsigned(3 downto 0);
   signal en1: std_logic;
begin
   -- register
   process(clk,reset)
   begin
      if (reset='1') then
         r_reg <= (others=>'0');
      elsif (clk'event and clk='1') then
         r_reg <= r_next;
      end if;
      if (r_reg = "1101") then
         en1 <= '1';
         else
            en1 <= '0';
      end if;
   end process;
   -- next-state logic
   r_next <= (others=>'0') when r_reg=(SIX-1) else
             r_reg + 1;
   -- output logic
   q <= std_logic_vector(r_reg);
   en <= en1;
end two_seg_arch;

Practica_5_codigo_VHDL/SixCounter.vhdl
library ieee;
use ieee.std_logic_1164.all;
use ieee.numeric_std.all;
entity mod6_counter is
   port(
      clk, reset: in std_logic;
      en: out std_logic;
      q: out std_logic_vector(3 downto 0)
   );
end mod6_counter;

architecture two_seg_arch of mod6_counter is
   constant SIX: integer := 6;
   signal r_reg: unsigned(3 downto 0);
   signal r_next: unsigned(3 downto 0);
   signal en1: std_logic;
begin
   -- register
   process(clk,reset)
   begin
      if (reset='1') then
         r_reg <= (others=>'0');
      elsif (clk'event and clk='1') then
         r_reg <= r_next;
      end if;
      if (r_reg = "0101") then
         en1 <= '1';
         else
            en1 <= '0';
      end if;
   end process;
   -- next-state logic
   r_next <= (others=>'0') when r_reg=(SIX-1) else
             r_reg + 1;
   -- output logic
   q <= std_logic_vector(r_reg);
   en <= en1;
end two_seg_arch;

Practica_5_codigo_VHDL/DecadeCounter.vhdl
library ieee;
use ieee.std_logic_1164.all;
use ieee.numeric_std.all;
entity mod10_counter is
   port(
      clk, reset: in std_logic;
      q: out std_logic_vector(3 downto 0);
      en: out std_logic
   );
end mod10_counter;

architecture two_seg_arch of mod10_counter is
   constant TEN: integer := 10;
   signal r_reg: unsigned(3 downto 0);
   signal r_next: unsigned(3 downto 0);
   signal en1: std_logic;
begin
   -- register
   process(clk,reset)
   begin
      if (reset='1') then
         r_reg <= (others=>'0');
      elsif (clk'event and clk='1') then
         r_reg <= r_next;
      end if;
      if (r_reg = "1001") then
         en1 <= '1';
         else
            en1 <= '0';
      end if;
   end process;
   -- next-state logic
   r_next <= (others=>'0') when r_reg=(TEN-1) else
             r_reg + 1;

   -- output logic
   q <= std_logic_vector(r_reg);
   en <= en1;
end two_seg_arch;

Practica_5_simulacion/Mod60Counter.vhdl
library ieee;
use ieee.numeric_bit.all;
use ieee.std_logic_1164.all;
entity mod60_Counter is
    port(
    clk, reset: in std_logic;
    x: out std_logic_vector(3 downto 0);    
    y: out std_logic_vector(3 downto 0); 
    z: out std_logic_vector(3 downto 0));     
end mod60_Counter;

architecture test of mod60_Counter is
    component mod10_counter is
        port(
           clk, reset: in std_logic;
           q: out std_logic_vector(3 downto 0);
           en: out std_logic
        );
    end component mod10_counter;
    component mod6_counter is
        port(
           clk, reset: in std_logic;
           q: out std_logic_vector(3 downto 0);
           en: out std_logic
        );
    end component mod6_counter;
    component mod13_counter is
        port(
           clk, reset: in std_logic;
           q: out std_logic_vector(3 downto 0);
           en: out std_logic
        );
    end component mod13_counter; 
    signal q1: std_logic_vector(3 downto 0);
    signal q2: std_logic_vector(3 downto 0);
    signal q3: std_logic_vector(3 downto 0);
    signal en: std_logic;
    signal en1: std_logic;
    signal en2: std_logic;
    begin
        FF0: mod10_counter port map(clk =>clk,reset => reset, q => q1,en => en);
        FF1: mod6_counter port map(clk => en,reset => reset, q => q2,en => en1);
        FF2: mod13_counter port map(clk =>en1,reset => reset, q => q3, en => en2);
        x <= q1;
        y <= q2;
        z <= q3;
 end test;

Practica_5_codigo_VHDL/Mod60Counter_tb.vhdl

library IEEE;
use IEEE.Std_logic_1164.all;
use IEEE.Numeric_Std.all;

entity mod60_Counter_tb is
end;

architecture bench of mod60_Counter_tb is

  component mod60_Counter
      port(
      clk, reset: in std_logic;
      x: out std_logic_vector(3 downto 0);    
      y: out std_logic_vector(3 downto 0); 
      z: out std_logic_vector(3 downto 0));     
  end component;

  signal clk, reset: std_logic;
  signal x: std_logic_vector(3 downto 0);
  signal y: std_logic_vector(3 downto 0);
  signal z: std_logic_vector(3 downto 0);
  constant clock_period: time := 1 ns;
  signal stop_the_clock: boolean;
begin

  uut: Mod60_Counter port map ( clk   => clk,
                                reset => reset,
                                x     => x,
                                y     => y,
                                z     => z );

        stimulus: process
        begin
                               
        -- Put initialisation code here
            reset <= '1';
            wait for 1 ns;                     
            reset <= '0';
            wait for 100 ns;
        -- Put test bench stimulus code here                        
        stop_the_clock <= true;
        wait;
    end process;
                              
    clocking: process
    begin
        while not stop_the_clock loop
        clk <= '0', '1' after clock_period / 2;
        wait for clock_period;
        end loop;
        wait;
    end process;

end;

Practica_5_codigo_VHDL/mod60_Counter_tb.vcd
$date
  Fri Apr 17 14:46:39 2020
$end
$version
  GHDL v0
$end
$timescale
  1 fs
$end
$scope module standard $end
$upscope $end
$scope module std_logic_1164 $end
$upscope $end
$scope module numeric_std $end
$upscope $end
$scope module numeric_bit $end
$upscope $end
$scope module mod60_counter_tb $end
$var reg 1 ! clk $end
$var reg 1 " reset $end
$var reg 4 # x[3:0] $end
$var reg 4 $ y[3:0] $end
$var reg 4 % z[3:0] $end
$var reg 1 & stop_the_clock $end
$scope module uut $end
$var reg 1 ' clk $end
$var reg 1 ( reset $end
$var reg 4 ) x[3:0] $end
$var reg 4 * y[3:0] $end
$var reg 4 + z[3:0] $end
$var reg 4 , q1[3:0] $end
$var reg 4 - q2[3:0] $end
$var reg 4 . q3[3:0] $end
$var reg 1 / en $end
$var reg 1 0 en1 $end
$var reg 1 1 en2 $end
$scope module ff0 $end
$var reg 1 2 clk $end
$var reg 1 3 reset $end
$var reg 4 4 q[3:0] $end
$var reg 1 5 en $end
$var reg 4 6 r_reg[3:0] $end
$var reg 4 7 r_next[3:0] $end
$var reg 1 8 en1 $end
$upscope $end
$scope module ff1 $end
$var reg 1 9 clk $end
$var reg 1 : reset $end
$var reg 1 ; en $end
$var reg 4 < q[3:0] $end
$var reg 4 = r_reg[3:0] $end
$var reg 4 > r_next[3:0] $end
$var reg 1 ? en1 $end
$upscope $end
$scope module ff2 $end
$var reg 1 @ clk $end
$var reg 1 A reset $end
$var reg 1 B en $end
$var reg 4 C q[3:0] $end
$var reg 4 D r_reg[3:0] $end
$var reg 4 E r_next[3:0] $end
$var reg 1 F en1 $end
$upscope $end
$upscope $end
$upscope $end
$enddefinitions $end
#0
0!
1"
b0000 #
b0000 $
b0000 %
0&
0'
1(
b0000 )
b0000 *
b0000 +
b0000 ,
b0000 -
b0000 .
0/
00
01
02
13
b0000 4
05
b0000 6
b0001 7
08
09
1:
0;
b0000 <
b0000 =
b0001 >
0?
0@
1A
0B
b0000 C
b0000 D
b0001 E
0F
#500000
1!
1'
12
#1000000
0!
0"
0'
0(
02
03
0:
0A
#1500000
1!
b0001 #
1'
b0001 )
b0001 ,
12
b0001 4
b0001 6
b0010 7
#2000000
0!
0'
02
#2500000
1!
b0010 #
1'
b0010 )
b0010 ,
12
b0010 4
b0010 6
b0011 7
#3000000
0!
0'
02
#3500000
1!
b0011 #
1'
b0011 )
b0011 ,
12
b0011 4
b0011 6
b0100 7
#4000000
0!
0'
02
#4500000
1!
b0100 #
1'
b0100 )
b0100 ,
12
b0100 4
b0100 6
b0101 7
#5000000
0!
0'
02
#5500000
1!
b0101 #
1'
b0101 )
b0101 ,
12
b0101 4
b0101 6
b0110 7
#6000000
0!
0'
02
#6500000
1!
b0110 #
1'
b0110 )
b0110 ,
12
b0110 4
b0110 6
b0111 7
#7000000
0!
0'
02
#7500000
1!
b0111 #
1'
b0111 )
b0111 ,
12
b0111 4
b0111 6
b1000 7
#8000000
0!
0'
02
#8500000
1!
b1000 #
1'
b1000 )
b1000 ,
12
b1000 4
b1000 6
b1001 7
#9000000
0!
0'
02
#9500000
1!
b1001 #
1'
b1001 )
b1001 ,
12
b1001 4
b1001 6
b0000 7
#10000000
0!
b0001 $
0'
b0001 *
b0001 -
1/
02
15
18
19
b0001 <
b0001 =
b0010 >
#10500000
1!
b0000 #
1'
b0000 )
b0000 ,
12
b0000 4
b0000 6
b0001 7
#11000000
0!
0'
0/
02
05
08
09
#11500000
1!
b0001 #
1'
b0001 )
b0001 ,
12
b0001 4
b0001 6
b0010 7
#12000000
0!
0'
02
#12500000
1!
b0010 #
1'
b0010 )
b0010 ,
12
b0010 4
b0010 6
b0011 7
#13000000
0!
0'
02
#13500000
1!
b0011 #
1'
b0011 )
b0011 ,
12
b0011 4
b0011 6
b0100 7
#14000000
0!
0'
02
#14500000
1!
b0100 #
1'
b0100 )
b0100 ,
12
b0100 4
b0100 6
b0101 7
#15000000
0!
0'
02
#15500000
1!
b0101 #
1'
b0101 )
b0101 ,
12
b0101 4
b0101 6
b0110 7
#16000000
0!
0'
02
#16500000
1!
b0110 #
1'
b0110 )
b0110 ,
12
b0110 4
b0110 6
b0111 7
#17000000
0!
0'
02
#17500000
1!
b0111 #
1'
b0111 )
b0111 ,
12
b0111 4
b0111 6
b1000 7
#18000000
0!
0'
02
#18500000
1!
b1000 #
1'
b1000 )
b1000 ,
12
b1000 4
b1000 6
b1001 7
#19000000
0!
0'
02
#19500000
1!
b1001 #
1'
b1001 )
b1001 ,
12
b1001 4
b1001 6
b0000 7
#20000000
0!
b0010 $
0'
b0010 *
b0010 -
1/
02
15
18
19
b0010 <
b0010 =
b0011 >
#20500000
1!
b0000 #
1'
b0000 )
b0000 ,
12
b0000 4
b0000 6
b0001 7
#21000000
0!
0'
0/
02
05
08
09
#21500000
1!
b0001 #
1'
b0001 )
b0001 ,
12
b0001 4
b0001 6
b0010 7
#22000000
0!
0'
02
#22500000
1!
b0010 #
1'
b0010 )
b0010 ,
12
b0010 4
b0010 6
b0011 7
#23000000
0!
0'
02
#23500000
1!
b0011 #
1'
b0011 )
b0011 ,
12
b0011 4
b0011 6
b0100 7
#24000000
0!
0'
02
#24500000
1!
b0100 #
1'
b0100 )
b0100 ,
12
b0100 4
b0100 6
b0101 7
#25000000
0!
0'
02
#25500000
1!
b0101 #
1'
b0101 )
b0101 ,
12
b0101 4
b0101 6
b0110 7
#26000000
0!
0'
02
#26500000
1!
b0110 #
1'
b0110 )
b0110 ,
12
b0110 4
b0110 6
b0111 7
#27000000
0!
0'
02
#27500000
1!
b0111 #
1'
b0111 )
b0111 ,
12
b0111 4
b0111 6
b1000 7
#28000000
0!
0'
02
#28500000
1!
b1000 #
1'
b1000 )
b1000 ,
12
b1000 4
b1000 6
b1001 7
#29000000
0!
0'
02
#29500000
1!
b1001 #
1'
b1001 )
b1001 ,
12
b1001 4
b1001 6
b0000 7
#30000000
0!
b0011 $
0'
b0011 *
b0011 -
1/
02
15
18
19
b0011 <
b0011 =
b0100 >
#30500000
1!
b0000 #
1'
b0000 )
b0000 ,
12
b0000 4
b0000 6
b0001 7
#31000000
0!
0'
0/
02
05
08
09
#31500000
1!
b0001 #
1'
b0001 )
b0001 ,
12
b0001 4
b0001 6
b0010 7
#32000000
0!
0'
02
#32500000
1!
b0010 #
1'
b0010 )
b0010 ,
12
b0010 4
b0010 6
b0011 7
#33000000
0!
0'
02
#33500000
1!
b0011 #
1'
b0011 )
b0011 ,
12
b0011 4
b0011 6
b0100 7
#34000000
0!
0'
02
#34500000
1!
b0100 #
1'
b0100 )
b0100 ,
12
b0100 4
b0100 6
b0101 7
#35000000
0!
0'
02
#35500000
1!
b0101 #
1'
b0101 )
b0101 ,
12
b0101 4
b0101 6
b0110 7
#36000000
0!
0'
02
#36500000
1!
b0110 #
1'
b0110 )
b0110 ,
12
b0110 4
b0110 6
b0111 7
#37000000
0!
0'
02
#37500000
1!
b0111 #
1'
b0111 )
b0111 ,
12
b0111 4
b0111 6
b1000 7
#38000000
0!
0'
02
#38500000
1!
b1000 #
1'
b1000 )
b1000 ,
12
b1000 4
b1000 6
b1001 7
#39000000
0!
0'
02
#39500000
1!
b1001 #
1'
b1001 )
b1001 ,
12
b1001 4
b1001 6
b0000 7
#40000000
0!
b0100 $
0'
b0100 *
b0100 -
1/
02
15
18
19
b0100 <
b0100 =
b0101 >
#40500000
1!
b0000 #
1'
b0000 )
b0000 ,
12
b0000 4
b0000 6
b0001 7
#41000000
0!
0'
0/
02
05
08
09
#41500000
1!
b0001 #
1'
b0001 )
b0001 ,
12
b0001 4
b0001 6
b0010 7
#42000000
0!
0'
02
#42500000
1!
b0010 #
1'
b0010 )
b0010 ,
12
b0010 4
b0010 6
b0011 7
#43000000
0!
0'
02
#43500000
1!
b0011 #
1'
b0011 )
b0011 ,
12
b0011 4
b0011 6
b0100 7
#44000000
0!
0'
02
#44500000
1!
b0100 #
1'
b0100 )
b0100 ,
12
b0100 4
b0100 6
b0101 7
#45000000
0!
0'
02
#45500000
1!
b0101 #
1'
b0101 )
b0101 ,
12
b0101 4
b0101 6
b0110 7
#46000000
0!
0'
02
#46500000
1!
b0110 #
1'
b0110 )
b0110 ,
12
b0110 4
b0110 6
b0111 7
#47000000
0!
0'
02
#47500000
1!
b0111 #
1'
b0111 )
b0111 ,
12
b0111 4
b0111 6
b1000 7
#48000000
0!
0'
02
#48500000
1!
b1000 #
1'
b1000 )
b1000 ,
12
b1000 4
b1000 6
b1001 7
#49000000
0!
0'
02
#49500000
1!
b1001 #
1'
b1001 )
b1001 ,
12
b1001 4
b1001 6
b0000 7
#50000000
0!
b0101 $
0'
b0101 *
b0101 -
1/
02
15
18
19
b0101 <
b0101 =
b0000 >
#50500000
1!
b0000 #
1'
b0000 )
b0000 ,
12
b0000 4
b0000 6
b0001 7
#51000000
0!
b0001 %
0'
b0001 +
b0001 .
0/
10
02
05
08
09
1;
1?
1@
b0001 C
b0001 D
b0010 E
#51500000
1!
b0001 #
1'
b0001 )
b0001 ,
12
b0001 4
b0001 6
b0010 7
#52000000
0!
0'
02
#52500000
1!
b0010 #
1'
b0010 )
b0010 ,
12
b0010 4
b0010 6
b0011 7
#53000000
0!
0'
02
#53500000
1!
b0011 #
1'
b0011 )
b0011 ,
12
b0011 4
b0011 6
b0100 7
#54000000
0!
0'
02
#54500000
1!
b0100 #
1'
b0100 )
b0100 ,
12
b0100 4
b0100 6
b0101 7
#55000000
0!
0'
02
#55500000
1!
b0101 #
1'
b0101 )
b0101 ,
12
b0101 4
b0101 6
b0110 7
#56000000
0!
0'
02
#56500000
1!
b0110 #
1'
b0110 )
b0110 ,
12
b0110 4
b0110 6
b0111 7
#57000000
0!
0'
02
#57500000
1!
b0111 #
1'
b0111 )
b0111 ,
12
b0111 4
b0111 6
b1000 7
#58000000
0!
0'
02
#58500000
1!
b1000 #
1'
b1000 )
b1000 ,
12
b1000 4
b1000 6
b1001 7
#59000000
0!
0'
02
#59500000
1!
b1001 #
1'
b1001 )
b1001 ,
12
b1001 4
b1001 6
b0000 7
#60000000
0!
b0000 $
0'
b0000 *
b0000 -
1/
02
15
18
19
b0000 <
b0000 =
b0001 >
#60500000
1!
b0000 #
1'
b0000 )
b0000 ,
12
b0000 4
b0000 6
b0001 7
#61000000
0!
0'
0/
00
02
05
08
09
0;
0?
0@
#61500000
1!
b0001 #
1'
b0001 )
b0001 ,
12
b0001 4
b0001 6
b0010 7
#62000000
0!
0'
02
#62500000
1!
b0010 #
1'
b0010 )
b0010 ,
12
b0010 4
b0010 6
b0011 7
#63000000
0!
0'
02
#63500000
1!
b0011 #
1'
b0011 )
b0011 ,
12
b0011 4
b0011 6
b0100 7
#64000000
0!
0'
02
#64500000
1!
b0100 #
1'
b0100 )
b0100 ,
12
b0100 4
b0100 6
b0101 7
#65000000
0!
0'
02
#65500000
1!
b0101 #
1'
b0101 )
b0101 ,
12
b0101 4
b0101 6
b0110 7
#66000000
0!
0'
02
#66500000
1!
b0110 #
1'
b0110 )
b0110 ,
12
b0110 4
b0110 6
b0111 7
#67000000
0!
0'
02
#67500000
1!
b0111 #
1'
b0111 )
b0111 ,
12
b0111 4
b0111 6
b1000 7
#68000000
0!
0'
02
#68500000
1!
b1000 #
1'
b1000 )
b1000 ,
12
b1000 4
b1000 6
b1001 7
#69000000
0!
0'
02
#69500000
1!
b1001 #
1'
b1001 )
b1001 ,
12
b1001 4
b1001 6
b0000 7
#70000000
0!
b0001 $
0'
b0001 *
b0001 -
1/
02
15
18
19
b0001 <
b0001 =
b0010 >
#70500000
1!
b0000 #
1'
b0000 )
b0000 ,
12
b0000 4
b0000 6
b0001 7
#71000000
0!
0'
0/
02
05
08
09
#71500000
1!
b0001 #
1'
b0001 )
b0001 ,
12
b0001 4
b0001 6
b0010 7
#72000000
0!
0'
02
#72500000
1!
b0010 #
1'
b0010 )
b0010 ,
12
b0010 4
b0010 6
b0011 7
#73000000
0!
0'
02
#73500000
1!
b0011 #
1'
b0011 )
b0011 ,
12
b0011 4
b0011 6
b0100 7
#74000000
0!
0'
02
#74500000
1!
b0100 #
1'
b0100 )
b0100 ,
12
b0100 4
b0100 6
b0101 7
#75000000
0!
0'
02
#75500000
1!
b0101 #
1'
b0101 )
b0101 ,
12
b0101 4
b0101 6
b0110 7
#76000000
0!
0'
02
#76500000
1!
b0110 #
1'
b0110 )
b0110 ,
12
b0110 4
b0110 6
b0111 7
#77000000
0!
0'
02
#77500000
1!
b0111 #
1'
b0111 )
b0111 ,
12
b0111 4
b0111 6
b1000 7
#78000000
0!
0'
02
#78500000
1!
b1000 #
1'
b1000 )
b1000 ,
12
b1000 4
b1000 6
b1001 7
#79000000
0!
0'
02
#79500000
1!
b1001 #
1'
b1001 )
b1001 ,
12
b1001 4
b1001 6
b0000 7
#80000000
0!
b0010 $
0'
b0010 *
b0010 -
1/
02
15
18
19
b0010 <
b0010 =
b0011 >
#80500000
1!
b0000 #
1'
b0000 )
b0000 ,
12
b0000 4
b0000 6
b0001 7
#81000000
0!
0'
0/
02
05
08
09
#81500000
1!
b0001 #
1'
b0001 )
b0001 ,
12
b0001 4
b0001 6
b0010 7
#82000000
0!
0'
02
#82500000
1!
b0010 #
1'
b0010 )
b0010 ,
12
b0010 4
b0010 6
b0011 7
#83000000
0!
0'
02
#83500000
1!
b0011 #
1'
b0011 )
b0011 ,
12
b0011 4
b0011 6
b0100 7
#84000000
0!
0'
02
#84500000
1!
b0100 #
1'
b0100 )
b0100 ,
12
b0100 4
b0100 6
b0101 7
#85000000
0!
0'
02
#85500000
1!
b0101 #
1'
b0101 )
b0101 ,
12
b0101 4
b0101 6
b0110 7
#86000000
0!
0'
02
#86500000
1!
b0110 #
1'
b0110 )
b0110 ,
12
b0110 4
b0110 6
b0111 7
#87000000
0!
0'
02
#87500000
1!
b0111 #
1'
b0111 )
b0111 ,
12
b0111 4
b0111 6
b1000 7
#88000000
0!
0'
02
#88500000
1!
b1000 #
1'
b1000 )
b1000 ,
12
b1000 4
b1000 6
b1001 7
#89000000
0!
0'
02
#89500000
1!
b1001 #
1'
b1001 )
b1001 ,
12
b1001 4
b1001 6
b0000 7
#90000000
0!
b0011 $
0'
b0011 *
b0011 -
1/
02
15
18
19
b0011 <
b0011 =
b0100 >
#90500000
1!
b0000 #
1'
b0000 )
b0000 ,
12
b0000 4
b0000 6
b0001 7
#91000000
0!
0'
0/
02
05
08
09
#91500000
1!
b0001 #
1'
b0001 )
b0001 ,
12
b0001 4
b0001 6
b0010 7
#92000000
0!
0'
02
#92500000
1!
b0010 #
1'
b0010 )
b0010 ,
12
b0010 4
b0010 6
b0011 7
#93000000
0!
0'
02
#93500000
1!
b0011 #
1'
b0011 )
b0011 ,
12
b0011 4
b0011 6
b0100 7
#94000000
0!
0'
02
#94500000
1!
b0100 #
1'
b0100 )
b0100 ,
12
b0100 4
b0100 6
b0101 7
#95000000
0!
0'
02
#95500000
1!
b0101 #
1'
b0101 )
b0101 ,
12
b0101 4
b0101 6
b0110 7
#96000000
0!
0'
02
#96500000
1!
b0110 #
1'
b0110 )
b0110 ,
12
b0110 4
b0110 6
b0111 7
#97000000
0!
0'
02
#97500000
1!
b0111 #
1'
b0111 )
b0111 ,
12
b0111 4
b0111 6
b1000 7
#98000000
0!
0'
02
#98500000
1!
b1000 #
1'
b1000 )
b1000 ,
12
b1000 4
b1000 6
b1001 7
#99000000
0!
0'
02
#99500000
1!
b1001 #
1'
b1001 )
b1001 ,
12
b1001 4
b1001 6
b0000 7
#100000000
0!
b0100 $
0'
b0100 *
b0100 -
1/
02
15
18
19
b0100 <
b0100 =
b0101 >
#100500000
1!
b0000 #
1'
b0000 )
b0000 ,
12
b0000 4
b0000 6
b0001 7
#101000000
0!
1&
0'
0/
02
05
08
09
#101500000
1!
b0001 #
1'
b0001 )
b0001 ,
12
b0001 4
b0001 6
b0010 7
