Examen Parcial/Codigo VHDL/FullAdder.vhdl
library IEEE;
use ieee.numeric_bit.all;
use ieee.std_logic_1164.all;
 
entity full_adder_vhdl_code is
 Port ( A : in BIT;
 B : in BIT;
 Cin : in BIT;
 S : out BIT;
 Cout : out BIT);
end full_adder_vhdl_code;
 
architecture test of full_adder_vhdl_code is
 
begin
 
 S <= A XOR B XOR Cin ;
 Cout <= (A AND B) OR (Cin AND A) OR (Cin AND B) ;
 
end test;

Examen Parcial/Codigo VHDL/Eightbit_Adder_Substractor.vhdl
library ieee;
use ieee.numeric_bit.all;
use ieee.std_logic_1164.all;

ENTITY addsub IS
   PORT (
      A : IN BIT_VECTOR(7 DOWNTO 0);
      B : IN BIT_VECTOR(7 DOWNTO 0); 
      T : IN BIT;
      C_FLAG : OUT BIT;
      OV_FLAG : OUT BIT;
      R : OUT BIT_VECTOR(7 DOWNTO 0)
   );
END addsub;
architecture test_adder of addsub is

--Declaracion de componente FullAdder

component full_adder_vhdl_code is
    Port ( A : in BIT;
    B : in BIT;
    Cin : in BIT;
    S : out BIT;
    Cout : out BIT);
   end component;

--Senales que se utilizan dentro del circuito

signal Cx : bit_vector(7 downto 0);
signal Bx : bit_vector(7 downto 0);
signal Sx : bit_vector(7 downto 0);
begin
	
Bx(0) <= B(0) xor T;
Bx(1) <= B(1) xor T;
Bx(2) <= B(2) xor T;
Bx(3) <= B(3) xor T;
Bx(4) <= B(4) xor T;
Bx(5) <= B(5) xor T;
Bx(6) <= B(6) xor T;
Bx(7) <= B(7) xor T;
F0 : full_adder_vhdl_code port map(A(0), Bx(0), T, Sx(0), Cx(0));
F1 : full_adder_vhdl_code port map(A(1), Bx(1), Cx(0), Sx(1), Cx(1));
F2 : full_adder_vhdl_code port map(A(2), Bx(2), Cx(1), Sx(2), Cx(2));
F3 : full_adder_vhdl_code port map(A(3), Bx(3), Cx(2), Sx(3), Cx(3));
F4 : full_adder_vhdl_code port map(A(4), Bx(4), Cx(3), Sx(4), Cx(4));
F5 : full_adder_vhdl_code port map(A(5), Bx(5), Cx(4), Sx(5), Cx(5));
F6 : full_adder_vhdl_code port map(A(6), Bx(6), Cx(5), Sx(6), Cx(6));
F7 : full_adder_vhdl_code port map(A(7), Bx(7), Cx(6), Sx(7), Cx(7));
R <= Sx;
C_FLAG <= Cx(7);
OV_FLAG <= ((A(7) and Bx(7) and (not Sx(7))) or ((not A(7)) and (not Bx(7)) and Sx(7))) or (Cx(6) xor Cx(7));
end architecture;

Examen Parcial/Codigo VHDL/Eightbit_Adder_Substractor_tb.vhdl
library IEEE;
use IEEE.Std_logic_1164.all;
use IEEE.Numeric_Std.all;

entity addsub_tb is
end;

architecture bench of addsub_tb is

  component addsub
     PORT (
        A : IN BIT_VECTOR(7 DOWNTO 0);
        B : IN BIT_VECTOR(7 DOWNTO 0); 
        T : IN BIT;
        C_FLAG : OUT BIT;
        OV_FLAG : OUT BIT;
        R : OUT BIT_VECTOR(7 DOWNTO 0)
     );
  end component;

  signal A: BIT_VECTOR(7 DOWNTO 0);
  signal B: BIT_VECTOR(7 DOWNTO 0);
  signal T: BIT;
  signal C_FLAG: BIT;
  signal OV_FLAG: BIT;
  signal R: BIT_VECTOR(7 DOWNTO 0) ;

begin

  uut: addsub port map ( A       => A,
                         B       => B,
                         T       => T,
                         C_FLAG  => C_FLAG,
                         OV_FLAG => OV_FLAG,
                         R       => R );

  stimulus: process
  begin
  
    -- Put initialisation code here
    --2 casos de suma de números positivos
    A <= "00011001";
    B <= "00000010";
    T <= '0';
    wait for 5 ns;
    A <= "00000100";
    B <= "00000010";
    T <= '0';
    wait for 5 ns;
    --2 casos de suma de número positivo y número negativo
    A <= "00000100";
    B <= "10000000";
    T <= '1';
    wait for 5 ns;
    A <= "00001000";
    B <= "10101110";
    T <= '1';
    -- 2 casos de suma de número negativo y número positivo
    wait for 5 ns;
    A <= "11100000";
    B <= "00000110";
    T <= '1';
    wait for 5 ns;
    A <= "11111000";
    B <= "00000110";
    T <= '1';
    -- 2 casos de overflow suma
    wait for 5 ns;
    A <= "01000000";
    B <= "01000000";
    T <= '0';
    wait for 5 ns;
    A <= "01100000";
    B <= "00100000";
    T <= '0';
    -- 2 casos de overflow resta
    wait for 5 ns;
    A <= "00000000";
    B <= "10000000";
    T <= '1';
    wait for 5 ns;
    A <= "01111000";
    B <= "11111000";
    T <= '1';
    -- 2 casos con carry out suma
    wait for 5 ns;
    A <= "01100000";
    B <= "10100000";
    T <= '0';
    wait for 5 ns;
    A <= "10100000";
    B <= "01100000";
    T <= '0';
    -- 2 casos con carry out resta
    wait for 5 ns;
    A <= "00001000";
    B <= "00001000";
    T <= '1';
    wait for 5 ns;
    A <= "00011000";
    B <= "00011000";
    T <= '1';
    wait for 5 ns;
      

    -- Put test bench stimulus code here

    wait;
  end process;


end;

Examen Parcial/Codigo VHDL/add_sub.vcd
$date
  Mon Mar 30 20:20:06 2020
$end
$version
  GHDL v0
$end
$timescale
  1 fs
$end
$scope module standard $end
$upscope $end
$scope module std_logic_1164 $end
$upscope $end
$scope module numeric_std $end
$upscope $end
$scope module numeric_bit $end
$upscope $end
$scope module addsub_tb $end
$var reg 8 ! a[7:0] $end
$var reg 8 " b[7:0] $end
$var reg 1 # t $end
$var reg 1 $ c_flag $end
$var reg 1 % ov_flag $end
$var reg 8 & r[7:0] $end
$scope module uut $end
$var reg 8 ' a[7:0] $end
$var reg 8 ( b[7:0] $end
$var reg 1 ) t $end
$var reg 1 * c_flag $end
$var reg 1 + ov_flag $end
$var reg 8 , r[7:0] $end
$var reg 8 - cx[7:0] $end
$var reg 8 . bx[7:0] $end
$var reg 8 / sx[7:0] $end
$scope module f0 $end
$var reg 1 0 a $end
$var reg 1 1 b $end
$var reg 1 2 cin $end
$var reg 1 3 s $end
$var reg 1 4 cout $end
$upscope $end
$scope module f1 $end
$var reg 1 5 a $end
$var reg 1 6 b $end
$var reg 1 7 cin $end
$var reg 1 8 s $end
$var reg 1 9 cout $end
$upscope $end
$scope module f2 $end
$var reg 1 : a $end
$var reg 1 ; b $end
$var reg 1 < cin $end
$var reg 1 = s $end
$var reg 1 > cout $end
$upscope $end
$scope module f3 $end
$var reg 1 ? a $end
$var reg 1 @ b $end
$var reg 1 A cin $end
$var reg 1 B s $end
$var reg 1 C cout $end
$upscope $end
$scope module f4 $end
$var reg 1 D a $end
$var reg 1 E b $end
$var reg 1 F cin $end
$var reg 1 G s $end
$var reg 1 H cout $end
$upscope $end
$scope module f5 $end
$var reg 1 I a $end
$var reg 1 J b $end
$var reg 1 K cin $end
$var reg 1 L s $end
$var reg 1 M cout $end
$upscope $end
$scope module f6 $end
$var reg 1 N a $end
$var reg 1 O b $end
$var reg 1 P cin $end
$var reg 1 Q s $end
$var reg 1 R cout $end
$upscope $end
$scope module f7 $end
$var reg 1 S a $end
$var reg 1 T b $end
$var reg 1 U cin $end
$var reg 1 V s $end
$var reg 1 W cout $end
$upscope $end
$upscope $end
$upscope $end
$enddefinitions $end
#0
b00011001 !
b00000010 "
0#
0$
0%
b00011011 &
b00011001 '
b00000010 (
0)
0*
0+
b00011011 ,
b00000000 -
b00000010 .
b00011011 /
10
01
02
13
04
05
16
07
18
09
0:
0;
0<
0=
0>
1?
0@
0A
1B
0C
1D
0E
0F
1G
0H
0I
0J
0K
0L
0M
0N
0O
0P
0Q
0R
0S
0T
0U
0V
0W
#5000000
b00000100 !
b00000110 &
b00000100 '
b00000110 ,
b00000110 /
00
03
1:
1=
0?
0B
0D
0G
#10000000
b10000000 "
1#
1%
b10000100 &
b10000000 (
1)
1+
b10000100 ,
b01111111 -
b01111111 .
b10000100 /
11
12
03
14
17
08
19
1;
1<
1=
1>
1@
1A
0B
1C
1E
1F
0G
1H
1J
1K
0L
1M
1O
1P
0Q
1R
1U
1V
#15000000
b00001000 !
b10101110 "
0%
b01011010 &
b00001000 '
b10101110 (
0+
b01011010 ,
b00000001 -
b01010001 .
b01011010 /
06
18
09
0:
0;
0<
0=
0>
1?
0@
0A
1B
0C
0F
1G
0H
0J
0K
0L
0M
0P
1Q
0R
0U
0V
#20000000
b11100000 !
b00000110 "
1$
0%
b11011010 &
b11100000 '
b00000110 (
1*
0+
b11011010 ,
b11100001 -
b11111001 .
b11011010 /
0?
1@
1B
1I
1J
0L
1M
1N
1P
1Q
1R
1S
1T
1U
1V
1W
#25000000
b11111000 !
b11110010 &
b11111000 '
b11110010 ,
b11111001 -
b11110010 /
1?
0B
1C
1D
1F
1G
1H
1K
1L
#30000000
b01000000 !
b01000000 "
0#
0$
1%
b10000000 &
b01000000 '
b01000000 (
0)
0*
1+
b10000000 ,
b01000000 -
b01000000 .
b10000000 /
01
02
03
04
07
08
0?
0@
0B
0C
0D
0E
0F
0G
0H
0I
0J
0K
0L
0M
0P
0Q
0S
0T
1V
0W
#35000000
b01100000 !
b00100000 "
b10000000 &
b01100000 '
b00100000 (
b10000000 ,
b01100000 -
b00100000 .
b10000000 /
1I
1J
0L
1M
0O
1P
0Q
1R
1U
1V
#40000000
b00000000 !
b10000000 "
1#
1%
b10000000 &
b00000000 '
b10000000 (
1)
1+
b10000000 ,
b01111111 -
b01111111 .
b10000000 /
11
12
03
14
16
17
08
19
1;
1<
0=
1>
1@
1A
0B
1C
1E
1F
0G
1H
0I
1K
0L
1M
0N
1O
1P
0Q
1R
1U
1V
#45000000
b01111000 !
b11111000 "
b10000000 &
b01111000 '
b11111000 (
b10000000 ,
b00000111 .
b10000000 /
1?
0@
0B
1D
0E
0G
1I
0J
0L
1N
0O
0Q
#50000000
b01100000 !
b10100000 "
0#
1$
0%
b00000000 &
b01100000 '
b10100000 (
0)
1*
0+
b00000000 ,
b11100000 -
b10100000 .
b00000000 /
01
02
03
04
06
07
09
0;
0<
0=
0>
0?
0A
0B
0C
0D
0F
0G
0H
1J
0K
1T
0V
1W
#55000000
b10100000 !
b01100000 "
1$
0%
b00000000 &
b10100000 '
b01100000 (
1*
0+
b00000000 ,
b11100000 -
b01100000 .
b00000000 /
0N
1O
0Q
1R
1S
0T
1U
0V
1W
#60000000
b00001000 !
b00001000 "
1#
1$
0%
b00000000 &
b00001000 '
b00001000 (
1)
1*
0+
b00000000 ,
b11111111 -
b11110111 .
b00000000 /
11
12
03
14
16
17
08
19
1;
1<
0=
1>
1?
1A
0B
1C
1E
1F
0G
1H
0I
1K
0L
1M
1P
0Q
1R
0S
1T
1U
0V
1W
#65000000
b00011000 !
b00011000 "
b00000000 &
b00011000 '
b00011000 (
b00000000 ,
b11100111 .
b00000000 /
1D
0E
0G
